Workbook

Sheet Financials>

Sheet Historical FS
B2: ="Historical Financial Statement - "&'Data Sheet'!B1 -> Historical Financial Statement - TATA MOTORS PASSENGER VEHICLES LTD
B3: Years | C3: ='Data Sheet'!B16 -> 42460 | D3: ='Data Sheet'!C16 -> 42825 | E3: ='Data Sheet'!D16 -> 43190 | F3: ='Data Sheet'!E16 -> 43555 | G3: ='Data Sheet'!F16 -> 43921 | H3: ='Data Sheet'!G16 -> 44286 | I3: ='Data Sheet'!H16 -> 44651 | J3: ='Data Sheet'!I16 -> 45016 | ... L3: ='Data Sheet'!K16 -> 45747 | M3: LTM
A5: # | B5: Income Statement
B6: Sales | C6: =IFERROR('Data Sheet'!B17,0) -> 273045.6 | D6: =IFERROR('Data Sheet'!C17,0) -> 269692.51 | E6: =IFERROR('Data Sheet'!D17,0) -> 291550.48 | F6: =IFERROR('Data Sheet'!E17,0) -> 301938.4 | G6: =IFERROR('Data Sheet'!F17,0) -> 261067.97 | H6: =IFERROR('Data Sheet'!G17,0) -> 249794.75 | I6: =IFERROR('Data Sheet'!H17,0) -> 278453.62 | J6: =IFERROR('Data Sheet'!I17,0) -> 345966.97 | ... L6: =IFERROR('Data Sheet'!K17,0) -> 439695 | M6: =IFERROR(SUM('Data Sheet'!H42:K42),0) -> 349637
B7: Sales Growth | C7: - | D7: =D6/C6-1 -> -0.01228033 | E7: =E6/D6-1 -> 0.081047746 | F7: =F6/E6-1 -> 0.035629919 | G7: =G6/F6-1 -> -0.13536016 | H7: =H6/G6-1 -> -0.043181168 | I7: =I6/H6-1 -> 0.11472967 | J7: =J6/I6-1 -> 0.24245815 | K7: =K6/J6-1 -> 0.25450126 | ... M7: =M6/L6-1 -> -0.20481925
B9: COGS | C9: =IFERROR(SUM('Data Sheet'!B18,'Data Sheet'!B20:B22)-1*'Data Sheet'!B19,0) -> 205509.07 | D9: =IFERROR(SUM('Data Sheet'!C18,'Data Sheet'!C20:C22)-1*'Data Sheet'!C19,0) -> 205454.24 | E9: =IFERROR(SUM('Data Sheet'!D18,'Data Sheet'!D20:D22)-1*'Data Sheet'!D19,0) -> 228429.83 | F9: =IFERROR(SUM('Data Sheet'!E18,'Data Sheet'!E20:E22)-1*'Data Sheet'!E19,0) -> 242845.53 | G9: =IFERROR(SUM('Data Sheet'!F18,'Data Sheet'!F20:F22)-1*'Data Sheet'!F19,0) -> 210376.07 | H9: =IFERROR(SUM('Data Sheet'!G18,'Data Sheet'!G20:G22)-1*'Data Sheet'!G19,0) -> 195326.04 | I9: =IFERROR(SUM('Data Sheet'!H18,'Data Sheet'!H20:H22)-1*'Data Sheet'!H19,0) -> 223300.01 | J9: =IFERROR(SUM('Data Sheet'!I18,'Data Sheet'!I20:I22)-1*'Data Sheet'!I19,0) -> 274403.64 | ... L9: =IFERROR(SUM('Data Sheet'!K18,'Data Sheet'!K20:K22)-1*'Data Sheet'!K19,0) -> 340809 | M9: =IFERROR(SUM('Data Sheet'!H43:K43),0) -> 325182
B10: COGS % Sales | C10: =C9/C6 -> 0.75265476 | D10: =D9/D6 -> 0.76180922 | E10: =E9/E6 -> 0.7835001 | F10: =F9/F6 -> 0.80428833 | G10: =G9/G6 -> 0.80582873 | H10: =H9/H6 -> 0.78194614 | I10: =I9/I6 -> 0.80192892 | J10: =J9/J6 -> 0.79314982 | ... M10: =M9/M6 -> 0.93005603
B12: Gross Profit | C12: =C6-C9 -> 67536.53 | D12: =D6-D9 -> 64238.27 | E12: =E6-E9 -> 63120.65 | F12: =F6-F9 -> 59092.87 | G12: =G6-G9 -> 50691.9 | H12: =H6-H9 -> 54468.71 | I12: =I6-I9 -> 55153.61 | J12: =J6-J9 -> 71563.33 | ... M12: =M6-M9 -> 24455
B13: Gross Margins | C13: =C12/C6 -> 0.24734524 | D13: =D12/D6 -> 0.23819078 | E13: =E12/E6 -> 0.2164999 | F13: =F12/F6 -> 0.19571167 | G13: =G12/G6 -> 0.19417127 | H13: =H12/H6 -> 0.21805386 | I13: =I12/I6 -> 0.19807108 | J13: =J12/J6 -> 0.20685018 | ... M13: =M12/M6 -> 0.06994397
B15: Selling & General Expenses | C15: =IFERROR(SUM('Data Sheet'!B23:B24),0) -> 29141.28 | D15: =IFERROR(SUM('Data Sheet'!C23:C24),0) -> 34649.58 | E15: =IFERROR(SUM('Data Sheet'!D23:D24),0) -> 31662.97 | F15: =IFERROR(SUM('Data Sheet'!E23:E24),0) -> 34428.54 | G15: =IFERROR(SUM('Data Sheet'!F23:F24),0) -> 32704.83 | H15: =IFERROR(SUM('Data Sheet'!G23:G24),0) -> 22181.28 | I15: =IFERROR(SUM('Data Sheet'!H23:H24),0) -> 30433.52 | J15: =IFERROR(SUM('Data Sheet'!I23:I24),0) -> 39747.53 | ... M15: =IFERROR(SUM('Data Sheet'!L23:L24),0) -> 0
B16: S&G Expenses % Sales | C16: =C15/C6 -> 0.10672679 | D16: =D15/D6 -> 0.1284781 | E16: =E15/E6 -> 0.10860202 | F16: =F15/F6 -> 0.11402505 | G16: =G15/G6 -> 0.12527324 | H16: =H15/H6 -> 0.088798023 | I16: =I15/I6 -> 0.10929475 | J16: =J15/J6 -> 0.11488822 | ... M16: =M15/M6 -> 0
B18: EBITDA | C18: =C12-C15 -> 38395.25 | D18: =D12-D15 -> 29588.69 | E18: =E12-E15 -> 31457.68 | F18: =F12-F15 -> 24664.33 | G18: =G12-G15 -> 17987.07 | H18: =H12-H15 -> 32287.43 | I18: =I12-I15 -> 24720.09 | J18: =J12-J15 -> 31815.8 | ... L18: =L12-L15 -> 56138
B19: EBITDA Margins | C19: =C18/C6 -> 0.14061845 | D19: =D18/D6 -> 0.10971269 | E19: =E18/E6 -> 0.10789788 | F19: =F18/F6 -> 0.081686629 | G19: =G18/G6 -> 0.068898034 | H19: =H18/H6 -> 0.12925584 | I19: =I18/I6 -> 0.088776328 | J19: =J18/J6 -> 0.091961958 | ... M19: =M18/M6 -> 0
B21: Interest | C21: =IFERROR('Data Sheet'!B27,0) -> 4889.08 | D21: =IFERROR('Data Sheet'!C27,0) -> 4238.01 | E21: =IFERROR('Data Sheet'!D27,0) -> 4681.79 | F21: =IFERROR('Data Sheet'!E27,0) -> 5758.6 | G21: =IFERROR('Data Sheet'!F27,0) -> 7243.33 | H21: =IFERROR('Data Sheet'!G27,0) -> 8097.17 | I21: =IFERROR('Data Sheet'!H27,0) -> 9311.86 | J21: =IFERROR('Data Sheet'!I27,0) -> 10225.48 | ... L21: =IFERROR('Data Sheet'!K27,0) -> 5083 | M21: =IFERROR(SUM('Data Sheet'!H46:K46),0) -> 3136
B22: Interest % Sales | C22: =C21/C6 -> 0.017905727 | D22: =D21/D6 -> 0.01571423 | E22: =E21/E6 -> 0.016058248 | F22: =F21/F6 -> 0.019072102 | G22: =G21/G6 -> 0.027744997 | H22: =H21/H6 -> 0.032415293 | I22: =I21/I6 -> 0.033441332 | J22: =J21/J6 -> 0.029556232 | ... M22: =M21/M6 -> 0.0089693024
B24: Depriciation | C24: =IFERROR('Data Sheet'!B26,0) -> 16710.78 | D24: =IFERROR('Data Sheet'!C26,0) -> 17904.99 | E24: =IFERROR('Data Sheet'!D26,0) -> 21553.59 | F24: =IFERROR('Data Sheet'!E26,0) -> 23590.63 | G24: =IFERROR('Data Sheet'!F26,0) -> 21425.43 | H24: =IFERROR('Data Sheet'!G26,0) -> 23546.71 | I24: =IFERROR('Data Sheet'!H26,0) -> 24835.69 | J24: =IFERROR('Data Sheet'!I26,0) -> 24860.36 | ... L24: =IFERROR('Data Sheet'!K26,0) -> 23256 | M24: =IFERROR(SUM('Data Sheet'!H45:K45),0) -> 19986
B25: Depriciation % Sales | C25: =C24/C6 -> 0.061201426 | D25: =D24/D6 -> 0.066390387 | E25: =E24/E6 -> 0.073927472 | F25: =F24/F6 -> 0.078130605 | G25: =G24/G6 -> 0.082068398 | H25: =H24/H6 -> 0.094264231 | I25: =I24/I6 -> 0.089191478 | J25: =J24/J6 -> 0.071857611 | ... M25: =M24/M6 -> 0.057162142
B27: Earnings Before Tax EBT | C27: =IFERROR(C18-SUM(C24,C21),0) -> 16795.39 | D27: =IFERROR(D18-SUM(D24,D21),0) -> 7445.69 | E27: =IFERROR(E18-SUM(E24,E21),0) -> 5222.3 | F27: =IFERROR(F18-SUM(F24,F21),0) -> -4684.9 | G27: =IFERROR(G18-SUM(G24,G21),0) -> -10681.69 | H27: =IFERROR(H18-SUM(H24,H21),0) -> 643.55 | I27: =IFERROR(I18-SUM(I24,I21),0) -> -9427.46 | J27: =IFERROR(J18-SUM(J24,J21),0) -> -3270.04 | ... L27: =IFERROR(L18-SUM(L24,L21),0) -> 27799 | M27: =IFERROR(SUM('Data Sheet'!H47:K47),0) -> 86626
B28: EBT % Sales | C28: =C27/C6 -> 0.061511301 | D28: =D27/D6 -> 0.027608071 | E28: =E27/E6 -> 0.017912164 | F28: =F27/F6 -> -0.015516079 | G28: =G27/G6 -> -0.04091536 | H28: =H27/H6 -> 0.0025763152 | I28: =I27/I6 -> -0.033856482 | J28: =J27/J6 -> -0.009451885 | ... M28: =M27/M6 -> 0.24775982
B30: Tax | C30: =IFERROR('Data Sheet'!B29,0) -> 3025.05 | D30: =IFERROR('Data Sheet'!C29,0) -> 3251.23 | E30: =IFERROR('Data Sheet'!D29,0) -> 4341.93 | F30: =IFERROR('Data Sheet'!E29,0) -> -2437.45 | G30: =IFERROR('Data Sheet'!F29,0) -> 395.25 | H30: =IFERROR('Data Sheet'!G29,0) -> 2541.86 | I30: =IFERROR('Data Sheet'!H29,0) -> 4231.29 | J30: =IFERROR('Data Sheet'!I29,0) -> 704.06 | ... L30: =IFERROR('Data Sheet'!K29,0) -> 10502 | M30: =IFERROR(SUM('Data Sheet'!H48:K48),0) -> 1302
B31: Effective Tax Rate | C31: =C30/C27 -> 0.18011192 | D31: =D30/D27 -> 0.43665933 | E31: =E30/E27 -> 0.83142102 | F31: =F30/F27 -> 0.52027791 | G31: =G30/G27 -> -0.037002572 | H31: =H30/H27 -> 3.9497475 | I31: =I30/I27 -> -0.44882609 | J31: =J30/J27 -> -0.21530623 | ... M31: =M30/M27 -> 0.01503013
B33: Net Profit | C33: =IFERROR(C27-C30,0) -> 13770.34 | D33: =IFERROR(D27-D30,0) -> 4194.46 | E33: =IFERROR(E27-E30,0) -> 880.37 | F33: =IFERROR(F27-F30,0) -> -2247.45 | G33: =IFERROR(G27-G30,0) -> -11076.94 | H33: =IFERROR(H27-H30,0) -> -1898.31 | I33: =IFERROR(I27-I30,0) -> -13658.75 | J33: =IFERROR(J27-J30,0) -> -3974.1 | ... L33: =IFERROR(L27-L30,0) -> 17297 | M33: =IFERROR(SUM('Data Sheet'!H49:K49),0) -> 85078
B34: Net Margins | C34: =C33/C6 -> 0.050432382 | D34: =D33/D6 -> 0.015552749 | E34: =E33/E6 -> 0.0030196143 | F34: =F33/F6 -> -0.0074434057 | G34: =G33/G6 -> -0.042429334 | H34: =H33/H6 -> -0.0075994792 | I34: =I33/I6 -> -0.049052155 | J34: =J33/J6 -> -0.011486935 | ... M34: =M33/M6 -> 0.24333237
B36: No. of Equity Shares | C36: =IFERROR('Data Sheet'!B93,0) -> 288.72 | D36: =IFERROR('Data Sheet'!C93,0) -> 288.73 | E36: =IFERROR('Data Sheet'!D93,0) -> 288.73 | F36: =IFERROR('Data Sheet'!E93,0) -> 288.73 | G36: =IFERROR('Data Sheet'!F93,0) -> 308.9 | H36: =IFERROR('Data Sheet'!G93,0) -> 332.03 | I36: =IFERROR('Data Sheet'!H93,0) -> 332.07 | J36: =IFERROR('Data Sheet'!I93,0) -> 332.13 | ... M36: =IFERROR('Data Sheet'!L93,0) -> 0
B38: Earning Per Share EPS | C38: =IFERROR(C33/C36,0) -> 47.694444 | D38: =IFERROR(D33/D36,0) -> 14.527275 | E38: =IFERROR(E33/E36,0) -> 3.0491116 | F38: =IFERROR(F33/F36,0) -> -7.7839158 | G38: =IFERROR(G33/G36,0) -> -35.859307 | H38: =IFERROR(H33/H36,0) -> -5.7172846 | I38: =IFERROR(I33/I36,0) -> -41.132141 | J38: =IFERROR(J33/J36,0) -> -11.965495 | ... M38: =IFERROR(M33/M36,0) -> 0
B39: EPS Growth % | C39: =IFERROR(C38/B38-1,0) -> 0 | D39: =IFERROR(D38/C38-1,0) -> -0.6954095 | E39: =IFERROR(E38/D38-1,0) -> -0.79011124 | F39: =IFERROR(F38/E38-1,0) -> -3.5528471 | G39: =IFERROR(G38/F38-1,0) -> 3.6068468 | H39: =IFERROR(H38/G38-1,0) -> -0.84056344 | I39: =IFERROR(I38/H38-1,0) -> 6.194349 | J39: =IFERROR(J38/I38-1,0) -> -0.70909622 | ... M39: =IFERROR(M38/L38-1,0) -> -1
B41: Dividend Per Share DPS | C41: =IFERROR('Data Sheet'!B31/'Historical FS'!C36,0) -> 0.23524522 | D41: =IFERROR('Data Sheet'!C31/'Historical FS'!D36,0) -> 0 | E41: =IFERROR('Data Sheet'!D31/'Historical FS'!E36,0) -> 0 | F41: =IFERROR('Data Sheet'!E31/'Historical FS'!F36,0) -> 0 | G41: =IFERROR('Data Sheet'!F31/'Historical FS'!G36,0) -> 0 | H41: =IFERROR('Data Sheet'!G31/'Historical FS'!H36,0) -> 0 | I41: =IFERROR('Data Sheet'!H31/'Historical FS'!I36,0) -> 0 | J41: =IFERROR('Data Sheet'!I31/'Historical FS'!J36,0) -> 2.3063861 | ... M41: =IFERROR('Data Sheet'!L31/'Historical FS'!M36,0) -> 0
B42: Dividend Payout Ratio | C42: =IFERROR(C41/C38,0) -> 0.0049323401 | D42: =IFERROR(D41/D38,0) -> 0 | E42: =IFERROR(E41/E38,0) -> 0 | F42: =IFERROR(F41/F38,0) -> 0 | G42: =IFERROR(G41/G38,0) -> 0 | H42: =IFERROR(H41/H38,0) -> 0 | I42: =IFERROR(I41/I38,0) -> 0 | J42: =IFERROR(J41/J38,0) -> -0.19275308 | ... L42: =IFERROR(L41/L38,0) -> 0.12765219 | M42: -
B44: Retained Earnings | C44: =IFERROR(IF(C38>C41,1-C42,0),0) -> 0.99506766 | D44: =IFERROR(IF(D38>D41,1-D42,0),0) -> 1 | E44: =IFERROR(IF(E38>E41,1-E42,0),0) -> 1 | F44: =IFERROR(IF(F38>F41,1-F42,0),0) -> 0 | G44: =IFERROR(IF(G38>G41,1-G42,0),0) -> 0 | H44: =IFERROR(IF(H38>H41,1-H42,0),0) -> 0 | I44: =IFERROR(IF(I38>I41,1-I42,0),0) -> 0 | J44: =IFERROR(IF(J38>J41,1-J42,0),0) -> 0 | ... M44: =IFERROR(IF(M38>M41,1-M42,0),0) -> 0
A46: # | B46: Balance Sheet
B47: Equity Share Capital | C47: =IFERROR('Data Sheet'!B57,0) -> 679.18 | D47: =IFERROR('Data Sheet'!C57,0) -> 679.22 | E47: =IFERROR('Data Sheet'!D57,0) -> 679.22 | F47: =IFERROR('Data Sheet'!E57,0) -> 679.22 | G47: =IFERROR('Data Sheet'!F57,0) -> 719.54 | H47: =IFERROR('Data Sheet'!G57,0) -> 765.81 | I47: =IFERROR('Data Sheet'!H57,0) -> 765.88 | J47: =IFERROR('Data Sheet'!I57,0) -> 766.02 | ... L47: =IFERROR('Data Sheet'!K57,0) -> 736
B48: Reserves | C48: =IFERROR('Data Sheet'!B58,0) -> 78273.23 | D48: =IFERROR('Data Sheet'!C58,0) -> 57382.67 | E48: =IFERROR('Data Sheet'!D58,0) -> 94748.69 | F48: =IFERROR('Data Sheet'!E58,0) -> 59500.34 | G48: =IFERROR('Data Sheet'!F58,0) -> 62358.99 | H48: =IFERROR('Data Sheet'!G58,0) -> 54480.91 | I48: =IFERROR('Data Sheet'!H58,0) -> 43795.36 | J48: =IFERROR('Data Sheet'!I58,0) -> 44555.77 | ... L48: =IFERROR('Data Sheet'!K58,0) -> 115408
B49: Borrowings | C49: =IFERROR('Data Sheet'!B59,0) -> 69359.96 | D49: =IFERROR('Data Sheet'!C59,0) -> 78603.98 | E49: =IFERROR('Data Sheet'!D59,0) -> 88950.47 | F49: =IFERROR('Data Sheet'!E59,0) -> 106175.34 | G49: =IFERROR('Data Sheet'!F59,0) -> 124787.64 | H49: =IFERROR('Data Sheet'!G59,0) -> 142130.57 | I49: =IFERROR('Data Sheet'!H59,0) -> 146449.03 | J49: =IFERROR('Data Sheet'!I59,0) -> 134113.44 | ... L49: =IFERROR('Data Sheet'!K59,0) -> 71540
B50: Other Liabilities | C50: =IFERROR('Data Sheet'!B60,0) -> 114871.75 | D50: =IFERROR('Data Sheet'!C60,0) -> 135914.49 | E50: =IFERROR('Data Sheet'!D60,0) -> 142813.43 | F50: =IFERROR('Data Sheet'!E60,0) -> 139348.59 | G50: =IFERROR('Data Sheet'!F60,0) -> 132313.22 | H50: =IFERROR('Data Sheet'!G60,0) -> 144192.62 | I50: =IFERROR('Data Sheet'!H60,0) -> 138051.22 | J50: =IFERROR('Data Sheet'!I60,0) -> 155239.2 | ... L50: =IFERROR('Data Sheet'!K60,0) -> 189289
B51: Total Liabilities | C51: =IFERROR('Data Sheet'!B61,0) -> 263184.12 | D51: =IFERROR('Data Sheet'!C61,0) -> 272580.36 | E51: =IFERROR('Data Sheet'!D61,0) -> 327191.81 | F51: =IFERROR('Data Sheet'!E61,0) -> 305703.49 | G51: =IFERROR('Data Sheet'!F61,0) -> 320179.39 | H51: =IFERROR('Data Sheet'!G61,0) -> 341569.91 | I51: =IFERROR('Data Sheet'!H61,0) -> 329061.49 | J51: =IFERROR('Data Sheet'!I61,0) -> 334674.43 | ... L51: =IFERROR('Data Sheet'!K61,0) -> 376973
B53: Fixed Assests Net Block | C53: =IFERROR('Data Sheet'!B62,0) -> 107231.76 | D53: =IFERROR('Data Sheet'!C62,0) -> 95944.08 | E53: =IFERROR('Data Sheet'!D62,0) -> 121413.86 | F53: =IFERROR('Data Sheet'!E62,0) -> 111234.47 | G53: =IFERROR('Data Sheet'!F62,0) -> 127107.14 | H53: =IFERROR('Data Sheet'!G62,0) -> 138707.61 | I53: =IFERROR('Data Sheet'!H62,0) -> 138855.45 | J53: =IFERROR('Data Sheet'!I62,0) -> 132079.76 | ... L53: =IFERROR('Data Sheet'!K62,0) -> 115697
B54: Capital Work in Progress | C54: =IFERROR('Data Sheet'!B63,0) -> 25918.94 | D54: =IFERROR('Data Sheet'!C63,0) -> 33698.84 | E54: =IFERROR('Data Sheet'!D63,0) -> 40033.5 | F54: =IFERROR('Data Sheet'!E63,0) -> 31883.84 | G54: =IFERROR('Data Sheet'!F63,0) -> 35622.29 | H54: =IFERROR('Data Sheet'!G63,0) -> 20963.93 | I54: =IFERROR('Data Sheet'!H63,0) -> 10251.09 | J54: =IFERROR('Data Sheet'!I63,0) -> 14274.5 | ... L54: =IFERROR('Data Sheet'!K63,0) -> 65806
B55: Investments | C55: =IFERROR('Data Sheet'!B64,0) -> 23767.02 | D55: =IFERROR('Data Sheet'!C64,0) -> 20337.92 | E55: =IFERROR('Data Sheet'!D64,0) -> 20812.75 | F55: =IFERROR('Data Sheet'!E64,0) -> 15770.72 | G55: =IFERROR('Data Sheet'!F64,0) -> 16308.48 | H55: =IFERROR('Data Sheet'!G64,0) -> 24620.28 | I55: =IFERROR('Data Sheet'!H64,0) -> 29379.53 | J55: =IFERROR('Data Sheet'!I64,0) -> 26379.16 | ... L55: =IFERROR('Data Sheet'!K64,0) -> 35656
B56: Other Assets | C56: =IFERROR('Data Sheet'!B65-SUM('Data Sheet'!B67:B69),0) -> 29579.36 | D56: =IFERROR('Data Sheet'!C65-SUM('Data Sheet'!C67:C69),0) -> 37360.78 | E56: =IFERROR('Data Sheet'!D65-SUM('Data Sheet'!D67:D69),0) -> 48286.86 | F56: =IFERROR('Data Sheet'!E65-SUM('Data Sheet'!E67:E69),0) -> 56155.74 | G56: =IFERROR('Data Sheet'!F65-SUM('Data Sheet'!F67:F69),0) -> 58784.94 | H56: =IFERROR('Data Sheet'!G65-SUM('Data Sheet'!G67:G69),0) -> 61717.96 | I56: =IFERROR('Data Sheet'!H65-SUM('Data Sheet'!H67:H69),0) -> 62223.77 | J56: =IFERROR('Data Sheet'!I65-SUM('Data Sheet'!I67:I69),0) -> 68432.09 | ... L56: =IFERROR('Data Sheet'!K65-SUM('Data Sheet'!K67:K69),0) -> 58463
B57: Total Non Current Assests | C57: =IFERROR(SUM(C53:C56),0) -> 186497.08 | D57: =IFERROR(SUM(D53:D56),0) -> 187341.62 | E57: =IFERROR(SUM(E53:E56),0) -> 230546.97 | F57: =IFERROR(SUM(F53:F56),0) -> 215044.77 | G57: =IFERROR(SUM(G53:G56),0) -> 237822.85 | H57: =IFERROR(SUM(H53:H56),0) -> 246009.78 | I57: =IFERROR(SUM(I53:I56),0) -> 240709.84 | J57: =IFERROR(SUM(J53:J56),0) -> 241165.51 | ... L57: =IFERROR(SUM(L53:L56),0) -> 275622
B59: Receivables | C59: =IFERROR('Data Sheet'!B67,0) -> 13570.91 | D59: =IFERROR('Data Sheet'!C67,0) -> 14075.55 | E59: =IFERROR('Data Sheet'!D67,0) -> 19893.3 | F59: =IFERROR('Data Sheet'!E67,0) -> 18996.17 | G59: =IFERROR('Data Sheet'!F67,0) -> 11172.69 | H59: =IFERROR('Data Sheet'!G67,0) -> 12679.08 | I59: =IFERROR('Data Sheet'!H67,0) -> 12442.12 | J59: =IFERROR('Data Sheet'!I67,0) -> 15737.97 | ... L59: =IFERROR('Data Sheet'!K67,0) -> 13248
B60: Inventory | C60: =IFERROR('Data Sheet'!B68,0) -> 32655.73 | D60: =IFERROR('Data Sheet'!C68,0) -> 35085.31 | E60: =IFERROR('Data Sheet'!D68,0) -> 42137.63 | F60: =IFERROR('Data Sheet'!E68,0) -> 39013.73 | G60: =IFERROR('Data Sheet'!F68,0) -> 37456.88 | H60: =IFERROR('Data Sheet'!G68,0) -> 36088.59 | I60: =IFERROR('Data Sheet'!H68,0) -> 35240.34 | J60: =IFERROR('Data Sheet'!I68,0) -> 40755.39 | ... L60: =IFERROR('Data Sheet'!K68,0) -> 47269
B61: Cash & Bank | C61: =IFERROR('Data Sheet'!B69,0) -> 30460.4 | D61: =IFERROR('Data Sheet'!C69,0) -> 36077.88 | E61: =IFERROR('Data Sheet'!D69,0) -> 34613.91 | F61: =IFERROR('Data Sheet'!E69,0) -> 32648.82 | G61: =IFERROR('Data Sheet'!F69,0) -> 33726.97 | H61: =IFERROR('Data Sheet'!G69,0) -> 46792.46 | I61: =IFERROR('Data Sheet'!H69,0) -> 40669.19 | J61: =IFERROR('Data Sheet'!I69,0) -> 37015.56 | ... L61: =IFERROR('Data Sheet'!K69,0) -> 40834
B62: Total Current Assests | C62: =IFERROR(SUM(C59:C61),0) -> 76687.04 | D62: =IFERROR(SUM(D59:D61),0) -> 85238.74 | E62: =IFERROR(SUM(E59:E61),0) -> 96644.84 | F62: =IFERROR(SUM(F59:F61),0) -> 90658.72 | G62: =IFERROR(SUM(G59:G61),0) -> 82356.54 | H62: =IFERROR(SUM(H59:H61),0) -> 95560.13 | I62: =IFERROR(SUM(I59:I61),0) -> 88351.65 | J62: =IFERROR(SUM(J59:J61),0) -> 93508.92 | ... L62: =IFERROR(SUM(L59:L61),0) -> 101351
B64: Total Assests | C64: =IFERROR(C62+C57,0) -> 263184.12 | D64: =IFERROR(D62+D57,0) -> 272580.36 | E64: =IFERROR(E62+E57,0) -> 327191.81 | F64: =IFERROR(F62+F57,0) -> 305703.49 | G64: =IFERROR(G62+G57,0) -> 320179.39 | H64: =IFERROR(H62+H57,0) -> 341569.91 | I64: =IFERROR(I62+I57,0) -> 329061.49 | J64: =IFERROR(J62+J57,0) -> 334674.43 | ... L64: =IFERROR(L62+L57,0) -> 376973
B66: Check | C66: =C64=C51 -> TRUE | D66: =D64=D51 -> TRUE | E66: =E64=E51 -> TRUE | F66: =F64=F51 -> TRUE | G66: =G64=G51 -> TRUE | H66: =H64=H51 -> TRUE | I66: =I64=I51 -> TRUE | J66: =J64=J51 -> TRUE | ... L66: =L64=L51 -> TRUE
A68: # | B68: Cash Flow Statement
B69: Operating Activities
B70: Profit from operations | C70: =IFERROR('Cash Flow Data'!E4,0) -> 38626 | D70: =IFERROR('Cash Flow Data'!F4,0) -> 28840 | E70: =IFERROR('Cash Flow Data'!G4,0) -> 33312 | F70: =IFERROR('Cash Flow Data'!H4,0) -> 28771 | G70: =IFERROR('Cash Flow Data'!I4,0) -> 23352 | H70: =IFERROR('Cash Flow Data'!J4,0) -> 31198 | I70: =IFERROR('Cash Flow Data'!K4,0) -> 26943 | J70: =IFERROR('Cash Flow Data'!L4,0) -> 41694 | ... L70: =IFERROR('Cash Flow Data'!N4,0) -> 58937
B71: Receivables | C71: =IFERROR('Cash Flow Data'!E5,0) -> -2223 | D71: =IFERROR('Cash Flow Data'!F5,0) -> -4152 | E71: =IFERROR('Cash Flow Data'!G5,0) -> -10688 | F71: =IFERROR('Cash Flow Data'!H5,0) -> -9109 | G71: =IFERROR('Cash Flow Data'!I5,0) -> 9950 | H71: =IFERROR('Cash Flow Data'!J5,0) -> -5505 | I71: =IFERROR('Cash Flow Data'!K5,0) -> 185 | J71: =IFERROR('Cash Flow Data'!L5,0) -> -2213 | ... L71: =IFERROR('Cash Flow Data'!N5,0) -> 3573
B72: Inventory | C72: =IFERROR('Cash Flow Data'!E6,0) -> -5743 | D72: =IFERROR('Cash Flow Data'!F6,0) -> -6621 | E72: =IFERROR('Cash Flow Data'!G6,0) -> -3560 | F72: =IFERROR('Cash Flow Data'!H6,0) -> 2069 | G72: =IFERROR('Cash Flow Data'!I6,0) -> 2326 | H72: =IFERROR('Cash Flow Data'!J6,0) -> 3814 | I72: =IFERROR('Cash Flow Data'!K6,0) -> 472 | J72: =IFERROR('Cash Flow Data'!L6,0) -> -5665 | ... L72: =IFERROR('Cash Flow Data'!N6,0) -> 2127
B73: Payables | C73: =IFERROR('Cash Flow Data'!E7,0) -> 3947 | D73: =IFERROR('Cash Flow Data'!F7,0) -> 9301 | E73: =IFERROR('Cash Flow Data'!G7,0) -> 7320 | F73: =IFERROR('Cash Flow Data'!H7,0) -> -4692 | G73: =IFERROR('Cash Flow Data'!I7,0) -> -8085 | H73: =IFERROR('Cash Flow Data'!J7,0) -> 5748 | I73: =IFERROR('Cash Flow Data'!K7,0) -> -7012 | J73: =IFERROR('Cash Flow Data'!L7,0) -> 6945 | ... L73: =IFERROR('Cash Flow Data'!N7,0) -> 1303
B74: Loans Advances | C74: =IFERROR('Cash Flow Data'!E8,0) -> -520 | D74: =IFERROR('Cash Flow Data'!F8,0) -> 0 | E74: =IFERROR('Cash Flow Data'!G8,0) -> 0 | F74: =IFERROR('Cash Flow Data'!H8,0) -> 0 | G74: =IFERROR('Cash Flow Data'!I8,0) -> 0 | H74: =IFERROR('Cash Flow Data'!J8,0) -> 0 | I74: =IFERROR('Cash Flow Data'!K8,0) -> 0 | J74: =IFERROR('Cash Flow Data'!L8,0) -> 0 | ... L74: =IFERROR('Cash Flow Data'!N8,0) -> 0
B75: Other WC items | C75: =IFERROR('Cash Flow Data'!E9,0) -> 5852 | D75: =IFERROR('Cash Flow Data'!F9,0) -> 4727 | E75: =IFERROR('Cash Flow Data'!G9,0) -> 494 | F75: =IFERROR('Cash Flow Data'!H9,0) -> 4512 | G75: =IFERROR('Cash Flow Data'!I9,0) -> 875 | H75: =IFERROR('Cash Flow Data'!J9,0) -> -4150 | I75: =IFERROR('Cash Flow Data'!K9,0) -> -4396 | J75: =IFERROR('Cash Flow Data'!L9,0) -> -2194 | ... L75: =IFERROR('Cash Flow Data'!N9,0) -> 1153
B76: Working capital changes | C76: =IFERROR('Cash Flow Data'!E10,0) -> 1313 | D76: =IFERROR('Cash Flow Data'!F10,0) -> 3254 | E76: =IFERROR('Cash Flow Data'!G10,0) -> -6434 | F76: =IFERROR('Cash Flow Data'!H10,0) -> -7221 | G76: =IFERROR('Cash Flow Data'!I10,0) -> 5065 | H76: =IFERROR('Cash Flow Data'!J10,0) -> -93 | I76: =IFERROR('Cash Flow Data'!K10,0) -> -10750 | J76: =IFERROR('Cash Flow Data'!L10,0) -> -3127 | ... L76: =IFERROR('Cash Flow Data'!N10,0) -> 8156
B77: Direct taxes | C77: =IFERROR('Cash Flow Data'!E11,0) -> -2040 | D77: =IFERROR('Cash Flow Data'!F11,0) -> -1895 | E77: =IFERROR('Cash Flow Data'!G11,0) -> -3021 | F77: =IFERROR('Cash Flow Data'!H11,0) -> -2659 | G77: =IFERROR('Cash Flow Data'!I11,0) -> -1785 | H77: =IFERROR('Cash Flow Data'!J11,0) -> -2105 | I77: =IFERROR('Cash Flow Data'!K11,0) -> -1910 | J77: =IFERROR('Cash Flow Data'!L11,0) -> -3179 | ... L77: =IFERROR('Cash Flow Data'!N11,0) -> -3991
B78: Cash from Operating Activities | C78: =IFERROR(SUM(C70:C77),0) -> 39212 | D78: =IFERROR(SUM(D70:D77),0) -> 33454 | E78: =IFERROR(SUM(E70:E77),0) -> 17423 | F78: =IFERROR(SUM(F70:F77),0) -> 11671 | G78: =IFERROR(SUM(G70:G77),0) -> 31698 | H78: =IFERROR(SUM(H70:H77),0) -> 28907 | I78: =IFERROR(SUM(I70:I77),0) -> 3532 | J78: =IFERROR(SUM(J70:J77),0) -> 32261 | ... L78: =IFERROR(SUM(L70:L77),0) -> 71258
B80: Investing Activities
B81: Fixed assets purchased | C81: =IFERROR('Cash Flow Data'!E13,0) -> -31503 | D81: =IFERROR('Cash Flow Data'!F13,0) -> -16072 | E81: =IFERROR('Cash Flow Data'!G13,0) -> -35079 | F81: =IFERROR('Cash Flow Data'!H13,0) -> -35304 | G81: =IFERROR('Cash Flow Data'!I13,0) -> -29702 | H81: =IFERROR('Cash Flow Data'!J13,0) -> -20205 | I81: =IFERROR('Cash Flow Data'!K13,0) -> -15168 | J81: =IFERROR('Cash Flow Data'!L13,0) -> -19230 | ... L81: =IFERROR('Cash Flow Data'!N13,0) -> -38042
B82: Fixed assets sold | C82: =IFERROR('Cash Flow Data'!E14,0) -> 59 | D82: =IFERROR('Cash Flow Data'!F14,0) -> 53 | E82: =IFERROR('Cash Flow Data'!G14,0) -> 30 | F82: =IFERROR('Cash Flow Data'!H14,0) -> 67 | G82: =IFERROR('Cash Flow Data'!I14,0) -> 171 | H82: =IFERROR('Cash Flow Data'!J14,0) -> 351 | I82: =IFERROR('Cash Flow Data'!K14,0) -> 230 | J82: =IFERROR('Cash Flow Data'!L14,0) -> 285 | ... L82: =IFERROR('Cash Flow Data'!N14,0) -> 974
B83: Investments purchased | C83: =IFERROR('Cash Flow Data'!E15,0) -> -4728 | D83: =IFERROR('Cash Flow Data'!F15,0) -> -6 | E83: =IFERROR('Cash Flow Data'!G15,0) -> -329 | F83: =IFERROR('Cash Flow Data'!H15,0) -> -130 | G83: =IFERROR('Cash Flow Data'!I15,0) -> -1439 | H83: =IFERROR('Cash Flow Data'!J15,0) -> -7530 | I83: =IFERROR('Cash Flow Data'!K15,0) -> -3008 | J83: =IFERROR('Cash Flow Data'!L15,0) -> -50 | ... L83: =IFERROR('Cash Flow Data'!N15,0) -> -12677
B84: Investments sold | C84: =IFERROR('Cash Flow Data'!E16,0) -> 89 | D84: =IFERROR('Cash Flow Data'!F16,0) -> 1965 | E84: =IFERROR('Cash Flow Data'!G16,0) -> 2381 | F84: =IFERROR('Cash Flow Data'!H16,0) -> 5644 | G84: =IFERROR('Cash Flow Data'!I16,0) -> 21 | H84: =IFERROR('Cash Flow Data'!J16,0) -> 226 | I84: =IFERROR('Cash Flow Data'!K16,0) -> 104 | J84: =IFERROR('Cash Flow Data'!L16,0) -> 6895 | ... L84: =IFERROR('Cash Flow Data'!N16,0) -> 111
B85: Interest received | C85: =IFERROR('Cash Flow Data'!E17,0) -> 731 | D85: =IFERROR('Cash Flow Data'!F17,0) -> 638 | E85: =IFERROR('Cash Flow Data'!G17,0) -> 690 | F85: =IFERROR('Cash Flow Data'!H17,0) -> 761 | G85: =IFERROR('Cash Flow Data'!I17,0) -> 1104 | H85: =IFERROR('Cash Flow Data'!J17,0) -> 428 | I85: =IFERROR('Cash Flow Data'!K17,0) -> 653 | J85: =IFERROR('Cash Flow Data'!L17,0) -> 973 | ... L85: =IFERROR('Cash Flow Data'!N17,0) -> 2420
B86: Dividends received | C86: =IFERROR('Cash Flow Data'!E18,0) -> 58 | D86: =IFERROR('Cash Flow Data'!F18,0) -> 620 | E86: =IFERROR('Cash Flow Data'!G18,0) -> 1797 | F86: =IFERROR('Cash Flow Data'!H18,0) -> 232 | G86: =IFERROR('Cash Flow Data'!I18,0) -> 21 | H86: =IFERROR('Cash Flow Data'!J18,0) -> 18 | I86: =IFERROR('Cash Flow Data'!K18,0) -> 32 | J86: =IFERROR('Cash Flow Data'!L18,0) -> 46 | ... L86: =IFERROR('Cash Flow Data'!N18,0) -> 64
B87: Investment in group cos | C87: =IFERROR('Cash Flow Data'!E19,0) -> 0 | D87: =IFERROR('Cash Flow Data'!F19,0) -> -107 | E87: =IFERROR('Cash Flow Data'!G19,0) -> -4 | F87: =IFERROR('Cash Flow Data'!H19,0) -> -9 | G87: =IFERROR('Cash Flow Data'!I19,0) -> -606 | H87: =IFERROR('Cash Flow Data'!J19,0) -> -10 | I87: =IFERROR('Cash Flow Data'!K19,0) -> 0 | J87: =IFERROR('Cash Flow Data'!L19,0) -> 0 | ... L87: =IFERROR('Cash Flow Data'!N19,0) -> 0
B88: Redemp n Canc of Shares | C88: =IFERROR('Cash Flow Data'!E20,0) -> 0 | D88: =IFERROR('Cash Flow Data'!F20,0) -> 0 | E88: =IFERROR('Cash Flow Data'!G20,0) -> 14 | F88: =IFERROR('Cash Flow Data'!H20,0) -> 533 | G88: =IFERROR('Cash Flow Data'!I20,0) -> 0 | H88: =IFERROR('Cash Flow Data'!J20,0) -> 0 | I88: =IFERROR('Cash Flow Data'!K20,0) -> 0 | J88: =IFERROR('Cash Flow Data'!L20,0) -> 19 | ... L88: =IFERROR('Cash Flow Data'!N20,0) -> 765
B89: Acquisition of companies | C89: =IFERROR('Cash Flow Data'!E21,0) -> -111 | D89: =IFERROR('Cash Flow Data'!F21,0) -> 0 | E89: =IFERROR('Cash Flow Data'!G21,0) -> 0 | F89: =IFERROR('Cash Flow Data'!H21,0) -> -8 | G89: =IFERROR('Cash Flow Data'!I21,0) -> -27 | H89: =IFERROR('Cash Flow Data'!J21,0) -> 0 | I89: =IFERROR('Cash Flow Data'!K21,0) -> -98 | J89: =IFERROR('Cash Flow Data'!L21,0) -> 0 | ... L89: =IFERROR('Cash Flow Data'!N21,0) -> -688
B90: Inter corporate deposits | C90: =IFERROR('Cash Flow Data'!E22,0) -> 0 | D90: =IFERROR('Cash Flow Data'!F22,0) -> 0 | E90: =IFERROR('Cash Flow Data'!G22,0) -> 0 | F90: =IFERROR('Cash Flow Data'!H22,0) -> 0 | G90: =IFERROR('Cash Flow Data'!I22,0) -> 0 | H90: =IFERROR('Cash Flow Data'!J22,0) -> 0 | I90: =IFERROR('Cash Flow Data'!K22,0) -> 0 | J90: =IFERROR('Cash Flow Data'!L22,0) -> 0 | ... L90: =IFERROR('Cash Flow Data'!N22,0) -> -20
B91: Other investing items | C91: =IFERROR('Cash Flow Data'!E23,0) -> -1289 | D91: =IFERROR('Cash Flow Data'!F23,0) -> -26663 | E91: =IFERROR('Cash Flow Data'!G23,0) -> 5360 | F91: =IFERROR('Cash Flow Data'!H23,0) -> 7335 | G91: =IFERROR('Cash Flow Data'!I23,0) -> -2659 | H91: =IFERROR('Cash Flow Data'!J23,0) -> 1051 | I91: =IFERROR('Cash Flow Data'!K23,0) -> 12813 | J91: =IFERROR('Cash Flow Data'!L23,0) -> -4357 | ... L91: =IFERROR('Cash Flow Data'!N23,0) -> -2889
B92: Cash from Investing Activities | C92: =IFERROR(SUM(C81:C91),0) -> -36694 | D92: =IFERROR(SUM(D81:D91),0) -> -39572 | E92: =IFERROR(SUM(E81:E91),0) -> -25140 | F92: =IFERROR(SUM(F81:F91),0) -> -20879 | G92: =IFERROR(SUM(G81:G91),0) -> -33116 | H92: =IFERROR(SUM(H81:H91),0) -> -25671 | I92: =IFERROR(SUM(I81:I91),0) -> -4442 | J92: =IFERROR(SUM(J81:J91),0) -> -15419 | ... L92: =IFERROR(SUM(L81:L91),0) -> -49982
B94: Financing Activities
B95: Proceeds from shares | C95: =IFERROR('Cash Flow Data'!E25,0) -> 7433 | D95: =IFERROR('Cash Flow Data'!F25,0) -> 5 | E95: =IFERROR('Cash Flow Data'!G25,0) -> 0 | F95: =IFERROR('Cash Flow Data'!H25,0) -> 0 | G95: =IFERROR('Cash Flow Data'!I25,0) -> 3889 | H95: =IFERROR('Cash Flow Data'!J25,0) -> 2603 | I95: =IFERROR('Cash Flow Data'!K25,0) -> 19 | J95: =IFERROR('Cash Flow Data'!L25,0) -> 20 | ... L95: =IFERROR('Cash Flow Data'!N25,0) -> 1108
B96: Redemption of debentures | C96: =IFERROR('Cash Flow Data'!E26,0) -> 0 | D96: =IFERROR('Cash Flow Data'!F26,0) -> 0 | E96: =IFERROR('Cash Flow Data'!G26,0) -> 0 | F96: =IFERROR('Cash Flow Data'!H26,0) -> 0 | G96: =IFERROR('Cash Flow Data'!I26,0) -> 0 | H96: =IFERROR('Cash Flow Data'!J26,0) -> 0 | I96: =IFERROR('Cash Flow Data'!K26,0) -> 0 | J96: =IFERROR('Cash Flow Data'!L26,0) -> 0 | ... L96: =IFERROR('Cash Flow Data'!N26,0) -> 0
B97: Proceeds from borrowings | C97: =IFERROR('Cash Flow Data'!E27,0) -> 19519 | D97: =IFERROR('Cash Flow Data'!F27,0) -> 33390 | E97: =IFERROR('Cash Flow Data'!G27,0) -> 37482 | F97: =IFERROR('Cash Flow Data'!H27,0) -> 51128 | G97: =IFERROR('Cash Flow Data'!I27,0) -> 38297 | H97: =IFERROR('Cash Flow Data'!J27,0) -> 46641 | I97: =IFERROR('Cash Flow Data'!K27,0) -> 46578 | J97: =IFERROR('Cash Flow Data'!L27,0) -> 43934 | ... L97: =IFERROR('Cash Flow Data'!N27,0) -> 13384
B98: Repayment of borrowings | C98: =IFERROR('Cash Flow Data'!E28,0) -> -24924 | D98: =IFERROR('Cash Flow Data'!F28,0) -> -21732 | E98: =IFERROR('Cash Flow Data'!G28,0) -> -29964 | F98: =IFERROR('Cash Flow Data'!H28,0) -> -35198 | G98: =IFERROR('Cash Flow Data'!I28,0) -> -29847 | H98: =IFERROR('Cash Flow Data'!J28,0) -> -29709 | I98: =IFERROR('Cash Flow Data'!K28,0) -> -42816 | J98: =IFERROR('Cash Flow Data'!L28,0) -> -62557 | ... L98: =IFERROR('Cash Flow Data'!N28,0) -> -21443
B99: Interest paid fin | C99: =IFERROR('Cash Flow Data'!E29,0) -> -5716 | D99: =IFERROR('Cash Flow Data'!F29,0) -> -5336 | E99: =IFERROR('Cash Flow Data'!G29,0) -> -5411 | F99: =IFERROR('Cash Flow Data'!H29,0) -> -7005 | G99: =IFERROR('Cash Flow Data'!I29,0) -> -7518 | H99: =IFERROR('Cash Flow Data'!J29,0) -> -8123 | I99: =IFERROR('Cash Flow Data'!K29,0) -> -9251 | J99: =IFERROR('Cash Flow Data'!L29,0) -> -9336 | ... L99: =IFERROR('Cash Flow Data'!N29,0) -> -5814
B100: Dividends paid | C100: =IFERROR('Cash Flow Data'!E30,0) -> -108 | D100: =IFERROR('Cash Flow Data'!F30,0) -> -121 | E100: =IFERROR('Cash Flow Data'!G30,0) -> -96 | F100: =IFERROR('Cash Flow Data'!H30,0) -> -95 | G100: =IFERROR('Cash Flow Data'!I30,0) -> -57 | H100: =IFERROR('Cash Flow Data'!J30,0) -> -30 | I100: =IFERROR('Cash Flow Data'!K30,0) -> -100 | J100: =IFERROR('Cash Flow Data'!L30,0) -> -141 | ... L100: =IFERROR('Cash Flow Data'!N30,0) -> -2492
B101: Financial liabilities | C101: =IFERROR('Cash Flow Data'!E31,0) -> 0 | D101: =IFERROR('Cash Flow Data'!F31,0) -> 0 | E101: =IFERROR('Cash Flow Data'!G31,0) -> 0 | F101: =IFERROR('Cash Flow Data'!H31,0) -> 0 | G101: =IFERROR('Cash Flow Data'!I31,0) -> -1346 | H101: =IFERROR('Cash Flow Data'!J31,0) -> -1477 | I101: =IFERROR('Cash Flow Data'!K31,0) -> -1559 | J101: =IFERROR('Cash Flow Data'!L31,0) -> -1517 | ... L101: =IFERROR('Cash Flow Data'!N31,0) -> -2393
B102: Other financing items | C102: =IFERROR('Cash Flow Data'!E32,0) -> 0 | D102: =IFERROR('Cash Flow Data'!F32,0) -> 0 | E102: =IFERROR('Cash Flow Data'!G32,0) -> 0 | F102: =IFERROR('Cash Flow Data'!H32,0) -> 0 | G102: =IFERROR('Cash Flow Data'!I32,0) -> -29 | H102: =IFERROR('Cash Flow Data'!J32,0) -> 0 | I102: =IFERROR('Cash Flow Data'!K32,0) -> 3750 | J102: =IFERROR('Cash Flow Data'!L32,0) -> 3355 | ... L102: =IFERROR('Cash Flow Data'!N32,0) -> -1136
B103: Cash From Financing Activities | C103: =IFERROR(SUM(C95:C102),0) -> -3796 | D103: =IFERROR(SUM(D95:D102),0) -> 6206 | E103: =IFERROR(SUM(E95:E102),0) -> 2011 | F103: =IFERROR(SUM(F95:F102),0) -> 8830 | G103: =IFERROR(SUM(G95:G102),0) -> 3389 | H103: =IFERROR(SUM(H95:H102),0) -> 9905 | I103: =IFERROR(SUM(I95:I102),0) -> -3379 | J103: =IFERROR(SUM(J95:J102),0) -> -26242 | ... L103: =IFERROR(SUM(L95:L102),0) -> -18786
B105: Net Cash Flow | C105: =IFERROR(SUM(C103+C92+C78),0) -> -1278 | D105: =IFERROR(SUM(D103+D92+D78),0) -> 88 | E105: =IFERROR(SUM(E103+E92+E78),0) -> -5706 | F105: =IFERROR(SUM(F103+F92+F78),0) -> -378 | G105: =IFERROR(SUM(G103+G92+G78),0) -> 1971 | H105: =IFERROR(SUM(H103+H92+H78),0) -> 13141 | I105: =IFERROR(SUM(I103+I92+I78),0) -> -4289 | J105: =IFERROR(SUM(J103+J92+J78),0) -> -9400 | ... L105: =IFERROR(SUM(L103+L92+L78),0) -> 2490

Sheet Ratio Analysis
B2: ="Ratio Analysis - "&'Data Sheet'!B1 -> Ratio Analysis - TATA MOTORS PASSENGER VEHICLES LTD
B3: Years | C3: ='Data Sheet'!B16 -> 42460 | D3: ='Data Sheet'!C16 -> 42825 | E3: ='Data Sheet'!D16 -> 43190 | F3: ='Data Sheet'!E16 -> 43555 | G3: ='Data Sheet'!F16 -> 43921 | H3: ='Data Sheet'!G16 -> 44286 | I3: ='Data Sheet'!H16 -> 44651 | J3: ='Data Sheet'!I16 -> 45016 | ... L3: ='Data Sheet'!K16 -> 45747 | M3: Trend | N3: Mean | O3: Median
B5: Sales Growth | C5: - | D5: =IFERROR('Historical FS'!D7,0) -> -0.01228033 | E5: =IFERROR('Historical FS'!E7,0) -> 0.081047746 | F5: =IFERROR('Historical FS'!F7,0) -> 0.035629919 | G5: =IFERROR('Historical FS'!G7,0) -> -0.13536016 | H5: =IFERROR('Historical FS'!H7,0) -> -0.043181168 | I5: =IFERROR('Historical FS'!I7,0) -> 0.11472967 | J5: =IFERROR('Historical FS'!J7,0) -> 0.24245815 | K5: =IFERROR('Historical FS'!K7,0) -> 0.25450126 | L5: =IFERROR('Historical FS'!L7,0) -> 0.013084771 | N5: =IFERROR(AVERAGE(D5:L5),0) -> 0.061181096 | O5: =IFERROR(MEDIAN(D5:L5),0) -> 0.035629919
B6: EBITDA Growth | C6: - | D6: =IFERROR(('Historical FS'!D18/'Historical FS'!C18)-1,0) -> -0.22936587 | E6: =IFERROR(('Historical FS'!E18/'Historical FS'!D18)-1,0) -> 0.063165689 | F6: =IFERROR(('Historical FS'!F18/'Historical FS'!E18)-1,0) -> -0.21595203 | G6: =IFERROR(('Historical FS'!G18/'Historical FS'!F18)-1,0) -> -0.27072538 | H6: =IFERROR(('Historical FS'!H18/'Historical FS'!G18)-1,0) -> 0.79503554 | I6: =IFERROR(('Historical FS'!I18/'Historical FS'!H18)-1,0) -> -0.23437418 | J6: =IFERROR(('Historical FS'!J18/'Historical FS'!I18)-1,0) -> 0.28704224 | K6: =IFERROR(('Historical FS'!K18/'Historical FS'!J18)-1,0) -> 0.8169903 | L6: =IFERROR(('Historical FS'!L18/'Historical FS'!K18)-1,0) -> -0.028905534 | N6: =IFERROR(AVERAGE(D6:L6),0) -> 0.10921231 | O6: =IFERROR(MEDIAN(D6:L6),0) -> -0.028905534
B7: EBIT Growth | C7: - | D7: =IFERROR(('Historical FS'!D27/'Historical FS'!C27)-1,0) -> -0.55668252 | E7: =IFERROR(('Historical FS'!E27/'Historical FS'!D27)-1,0) -> -0.29861437 | F7: =IFERROR(('Historical FS'!F27/'Historical FS'!E27)-1,0) -> -1.8970951 | G7: =IFERROR(('Historical FS'!G27/'Historical FS'!F27)-1,0) -> 1.2800252 | H7: =IFERROR(('Historical FS'!H27/'Historical FS'!G27)-1,0) -> -1.060248 | I7: =IFERROR(('Historical FS'!I27/'Historical FS'!H27)-1,0) -> -15.649149 | J7: =IFERROR(('Historical FS'!J27/'Historical FS'!I27)-1,0) -> -0.65313669 | K7: =IFERROR(('Historical FS'!K27/'Historical FS'!J27)-1,0) -> -8.0262137 | L7: =IFERROR(('Historical FS'!L27/'Historical FS'!K27)-1,0) -> 0.20991469 | N7: =IFERROR(AVERAGE(D7:L7),0) -> -2.9612444 | O7: =IFERROR(MEDIAN(D7:L7),0) -> -0.65313669
B8: Net Profit Growth | C8: - | D8: =IFERROR(('Historical FS'!D33/'Historical FS'!C33)-1,0) -> -0.69539895 | E8: =IFERROR(('Historical FS'!E33/'Historical FS'!D33)-1,0) -> -0.79011124 | F8: =IFERROR(('Historical FS'!F33/'Historical FS'!E33)-1,0) -> -3.5528471 | G8: =IFERROR(('Historical FS'!G33/'Historical FS'!F33)-1,0) -> 3.9286703 | H8: =IFERROR(('Historical FS'!H33/'Historical FS'!G33)-1,0) -> -0.82862505 | I8: =IFERROR(('Historical FS'!I33/'Historical FS'!H33)-1,0) -> 6.1952157 | J8: =IFERROR(('Historical FS'!J33/'Historical FS'!I33)-1,0) -> -0.70904365 | K8: =IFERROR(('Historical FS'!K33/'Historical FS'!J33)-1,0) -> -7.7939911 | L8: =IFERROR(('Historical FS'!L33/'Historical FS'!K33)-1,0) -> -0.35937037 | N8: =IFERROR(AVERAGE(D8:L8),0) -> -0.51172238 | O8: =IFERROR(MEDIAN(D8:L8),0) -> -0.70904365
B9: Dividend Growth | C9: - | D9: =IFERROR(('Historical FS'!D41/'Historical FS'!C41)-1,0) -> -1 | E9: =IFERROR(('Historical FS'!E41/'Historical FS'!D41)-1,0) -> 0 | F9: =IFERROR(('Historical FS'!F41/'Historical FS'!E41)-1,0) -> 0 | G9: =IFERROR(('Historical FS'!G41/'Historical FS'!F41)-1,0) -> 0 | H9: =IFERROR(('Historical FS'!H41/'Historical FS'!G41)-1,0) -> 0 | I9: =IFERROR(('Historical FS'!I41/'Historical FS'!H41)-1,0) -> 0 | J9: =IFERROR(('Historical FS'!J41/'Historical FS'!I41)-1,0) -> 0 | K9: =IFERROR(('Historical FS'!K41/'Historical FS'!J41)-1,0) -> 2.001669 | L9: =IFERROR(('Historical FS'!L41/'Historical FS'!K41)-1,0) -> -0.1336307 | N9: =IFERROR(AVERAGE(D9:L9),0) -> 0.096448699 | O9: =IFERROR(MEDIAN(D9:L9),0) -> 0
B11: Gross Margins | C11: =IFERROR('Historical FS'!C13,0) -> 0.24734524 | D11: =IFERROR('Historical FS'!D13,0) -> 0.23819078 | E11: =IFERROR('Historical FS'!E13,0) -> 0.2164999 | F11: =IFERROR('Historical FS'!F13,0) -> 0.19571167 | G11: =IFERROR('Historical FS'!G13,0) -> 0.19417127 | H11: =IFERROR('Historical FS'!H13,0) -> 0.21805386 | I11: =IFERROR('Historical FS'!I13,0) -> 0.19807108 | J11: =IFERROR('Historical FS'!J13,0) -> 0.20685018 | ... L11: =IFERROR('Historical FS'!L13,0) -> 0.2248968 | N11: =IFERROR(AVERAGE(C11:L11),0) -> 0.21693584 | O11: =IFERROR(MEDIAN(D11:L11),0) -> 0.2164999
B12: EBITDA Margins | C12: =IFERROR('Historical FS'!C19,0) -> 0.14061845 | D12: =IFERROR('Historical FS'!D19,0) -> 0.10971269 | E12: =IFERROR('Historical FS'!E19,0) -> 0.10789788 | F12: =IFERROR('Historical FS'!F19,0) -> 0.081686629 | G12: =IFERROR('Historical FS'!G19,0) -> 0.068898034 | H12: =IFERROR('Historical FS'!H19,0) -> 0.12925584 | I12: =IFERROR('Historical FS'!I19,0) -> 0.088776328 | J12: =IFERROR('Historical FS'!J19,0) -> 0.091961958 | ... L12: =IFERROR('Historical FS'!L19,0) -> 0.12767487 | N12: =IFERROR(AVERAGE(C12:L12),0) -> 0.10796782 | O12: =IFERROR(MEDIAN(D12:L12),0) -> 0.10789788
B13: EBIT Margins | C13: =IFERROR((('Historical FS'!C18-'Historical FS'!C24)/'Historical FS'!C6),0) -> 0.079417028 | D13: =IFERROR((('Historical FS'!D18-'Historical FS'!D24)/'Historical FS'!D6),0) -> 0.043322301 | E13: =IFERROR((('Historical FS'!E18-'Historical FS'!E24)/'Historical FS'!E6),0) -> 0.033970412 | F13: =IFERROR((('Historical FS'!F18-'Historical FS'!F24)/'Historical FS'!F6),0) -> 0.0035560233 | G13: =IFERROR((('Historical FS'!G18-'Historical FS'!G24)/'Historical FS'!G6),0) -> -0.013170363 | H13: =IFERROR((('Historical FS'!H18-'Historical FS'!H24)/'Historical FS'!H6),0) -> 0.034991608 | I13: =IFERROR((('Historical FS'!I18-'Historical FS'!I24)/'Historical FS'!I6),0) -> -0.00041514993 | J13: =IFERROR((('Historical FS'!J18-'Historical FS'!J24)/'Historical FS'!J6),0) -> 0.020104347 | ... L13: =IFERROR((('Historical FS'!L18-'Historical FS'!L24)/'Historical FS'!L6),0) -> 0.074783657 | N13: =IFERROR(AVERAGE(C13:L13),0) -> 0.034699505 | O13: =IFERROR(MEDIAN(D13:L13),0) -> 0.033970412
B14: EBT Margins | C14: =IFERROR('Historical FS'!C28,0) -> 0.061511301 | D14: =IFERROR('Historical FS'!D28,0) -> 0.027608071 | E14: =IFERROR('Historical FS'!E28,0) -> 0.017912164 | F14: =IFERROR('Historical FS'!F28,0) -> -0.015516079 | G14: =IFERROR('Historical FS'!G28,0) -> -0.04091536 | H14: =IFERROR('Historical FS'!H28,0) -> 0.0025763152 | I14: =IFERROR('Historical FS'!I28,0) -> -0.033856482 | J14: =IFERROR('Historical FS'!J28,0) -> -0.009451885 | ... L14: =IFERROR('Historical FS'!L28,0) -> 0.063223371 | N14: =IFERROR(AVERAGE(C14:L14),0) -> 0.012602956 | O14: =IFERROR(MEDIAN(D14:L14),0) -> 0.0025763152
B15: Net Profit Margins | C15: =IFERROR('Historical FS'!C34,0) -> 0.050432382 | D15: =IFERROR('Historical FS'!D34,0) -> 0.015552749 | E15: =IFERROR('Historical FS'!E34,0) -> 0.0030196143 | F15: =IFERROR('Historical FS'!F34,0) -> -0.0074434057 | G15: =IFERROR('Historical FS'!G34,0) -> -0.042429334 | H15: =IFERROR('Historical FS'!H34,0) -> -0.0075994792 | I15: =IFERROR('Historical FS'!I34,0) -> -0.049052155 | J15: =IFERROR('Historical FS'!J34,0) -> -0.011486935 | ... L15: =IFERROR('Historical FS'!L34,0) -> 0.039338632 | N15: =IFERROR(AVERAGE(C15:L15),0) -> 0.0052541758 | O15: =IFERROR(MEDIAN(D15:L15),0) -> -0.0074434057
B17: Sales Expenses % Sales | C17: =IFERROR('Historical FS'!C16,0) -> 0.10672679 | D17: =IFERROR('Historical FS'!D16,0) -> 0.1284781 | E17: =IFERROR('Historical FS'!E16,0) -> 0.10860202 | F17: =IFERROR('Historical FS'!F16,0) -> 0.11402505 | G17: =IFERROR('Historical FS'!G16,0) -> 0.12527324 | H17: =IFERROR('Historical FS'!H16,0) -> 0.088798023 | I17: =IFERROR('Historical FS'!I16,0) -> 0.10929475 | J17: =IFERROR('Historical FS'!J16,0) -> 0.11488822 | ... L17: =IFERROR('Historical FS'!L16,0) -> 0.097221938 | N17: =IFERROR(AVERAGE(C17:L17),0) -> 0.10896801 | O17: =IFERROR(MEDIAN(D17:L17),0) -> 0.10929475
B18: Depreciation % Sales | C18: =IFERROR('Historical FS'!C25,0) -> 0.061201426 | D18: =IFERROR('Historical FS'!D25,0) -> 0.066390387 | E18: =IFERROR('Historical FS'!E25,0) -> 0.073927472 | F18: =IFERROR('Historical FS'!F25,0) -> 0.078130605 | G18: =IFERROR('Historical FS'!G25,0) -> 0.082068398 | H18: =IFERROR('Historical FS'!H25,0) -> 0.094264231 | I18: =IFERROR('Historical FS'!I25,0) -> 0.089191478 | J18: =IFERROR('Historical FS'!J25,0) -> 0.071857611 | ... L18: =IFERROR('Historical FS'!L25,0) -> 0.052891209 | N18: =IFERROR(AVERAGE(C18:L18),0) -> 0.073268318 | O18: =IFERROR(MEDIAN(D18:L18),0) -> 0.073927472
B19: Operating Income % Sales | C19: =C13 -> 0.079417028 | D19: =D13 -> 0.043322301 | E19: =E13 -> 0.033970412 | F19: =F13 -> 0.0035560233 | G19: =G13 -> -0.013170363 | H19: =H13 -> 0.034991608 | I19: =I13 -> -0.00041514993 | J19: =J13 -> 0.020104347 | ... L19: =L13 -> 0.074783657 | N19: =IFERROR(AVERAGE(C19:L19),0) -> 0.034699505 | O19: =IFERROR(MEDIAN(D19:L19),0) -> 0.033970412
B21: Return on Capital Employed | C21: =IFERROR(('Historical FS'!C18-'Historical FS'!C24)/(SUM('Historical FS'!C47:C49)),0) -> 0.1462081 | D21: =IFERROR(('Historical FS'!D18-'Historical FS'!D24)/(SUM('Historical FS'!D47:D49)),0) -> 0.085490986 | E21: =IFERROR(('Historical FS'!E18-'Historical FS'!E24)/(SUM('Historical FS'!E47:E49)),0) -> 0.053716114 | F21: =IFERROR(('Historical FS'!F18-'Historical FS'!F24)/(SUM('Historical FS'!F47:F49)),0) -> 0.0064542734 | G21: =IFERROR(('Historical FS'!G18-'Historical FS'!G24)/(SUM('Historical FS'!G47:G49)),0) -> -0.018302178 | H21: =IFERROR(('Historical FS'!H18-'Historical FS'!H24)/(SUM('Historical FS'!H47:H49)),0) -> 0.044284325 | I21: =IFERROR(('Historical FS'!I18-'Historical FS'!I24)/(SUM('Historical FS'!I47:I49)),0) -> -0.00060520306 | J21: =IFERROR(('Historical FS'!J18-'Historical FS'!J24)/(SUM('Historical FS'!J47:J49)),0) -> 0.038762956 | ... L21: =IFERROR(('Historical FS'!L18-'Historical FS'!L24)/(SUM('Historical FS'!L47:L49)),0) -> 0.17519874 | N21: =IFERROR(AVERAGE(C21:L21),0) -> 0.069027608 | O21: =IFERROR(MEDIAN(D21:L21),0) -> 0.044284325
B22: Return on Earnings % | C22: =IFERROR('Historical FS'!C44,0) -> 0.99506766 | D22: =IFERROR('Historical FS'!D44,0) -> 1 | E22: =IFERROR('Historical FS'!E44,0) -> 1 | F22: =IFERROR('Historical FS'!F44,0) -> 0 | G22: =IFERROR('Historical FS'!G44,0) -> 0 | H22: =IFERROR('Historical FS'!H44,0) -> 0 | I22: =IFERROR('Historical FS'!I44,0) -> 0 | J22: =IFERROR('Historical FS'!J44,0) -> 0 | ... L22: =IFERROR('Historical FS'!L44,0) -> 0.87234781 | N22: =IFERROR(AVERAGE(C22:L22),0) -> 0.47821932 | O22: =IFERROR(MEDIAN(D22:L22),0) -> 0
B23: Return on Equity % | C23: =IFERROR('Historical FS'!C33/(SUM('Historical FS'!C47:C48)),0) -> 0.17441317 | D23: =IFERROR('Historical FS'!D33/(SUM('Historical FS'!D47:D48)),0) -> 0.07224119 | E23: =IFERROR('Historical FS'!E33/(SUM('Historical FS'!E47:E48)),0) -> 0.0092254981 | F23: =IFERROR('Historical FS'!F33/(SUM('Historical FS'!F47:F48)),0) -> -0.037345737 | G23: =IFERROR('Historical FS'!G33/(SUM('Historical FS'!G47:G48)),0) -> -0.17560555 | H23: =IFERROR('Historical FS'!H33/(SUM('Historical FS'!H47:H48)),0) -> -0.034360592 | I23: =IFERROR('Historical FS'!I33/(SUM('Historical FS'!I47:I48)),0) -> -0.30651638 | J23: =IFERROR('Historical FS'!J33/(SUM('Historical FS'!J47:J48)),0) -> -0.087686298 | ... L23: =IFERROR('Historical FS'!L33/(SUM('Historical FS'!L47:L48)),0) -> 0.14892719 | N23: =IFERROR(AVERAGE(C23:L23),0) -> 0.0081246283 | O23: =IFERROR(MEDIAN(D23:L23),0) -> -0.034360592
B24: Self Sustained Growth Rate | C24: =IFERROR(C22*C23,0) -> 0.1735529 | D24: =IFERROR(D22*D23,0) -> 0.07224119 | E24: =IFERROR(E22*E23,0) -> 0.0092254981 | F24: =IFERROR(F22*F23,0) -> 0 | G24: =IFERROR(G22*G23,0) -> 0 | H24: =IFERROR(H22*H23,0) -> 0 | I24: =IFERROR(I22*I23,0) -> 0 | J24: =IFERROR(J22*J23,0) -> 0 | ... L24: =IFERROR(L22*L23,0) -> 0.12991631 | N24: =IFERROR(AVERAGE(C24:L24),0) -> 0.067579296 | O24: =IFERROR(MEDIAN(D24:L24),0) -> 0
B25: Interest Coverage Ratio | C25: =IFERROR(('Historical FS'!C18-'Historical FS'!C24)/'Historical FS'!C21,0) -> 4.4352864 | D25: =IFERROR(('Historical FS'!D18-'Historical FS'!D24)/'Historical FS'!D21,0) -> 2.7568835 | E25: =IFERROR(('Historical FS'!E18-'Historical FS'!E24)/'Historical FS'!E21,0) -> 2.1154494 | F25: =IFERROR(('Historical FS'!F18-'Historical FS'!F24)/'Historical FS'!F21,0) -> 0.18645157 | G25: =IFERROR(('Historical FS'!G18-'Historical FS'!G24)/'Historical FS'!G21,0) -> -0.47469327 | H25: =IFERROR(('Historical FS'!H18-'Historical FS'!H24)/'Historical FS'!H21,0) -> 1.0794784 | I25: =IFERROR(('Historical FS'!I18-'Historical FS'!I24)/'Historical FS'!I21,0) -> -0.012414276 | J25: =IFERROR(('Historical FS'!J18-'Historical FS'!J24)/'Historical FS'!J21,0) -> 0.6802067 | ... L25: =IFERROR(('Historical FS'!L18-'Historical FS'!L24)/'Historical FS'!L21,0) -> 6.4690144 | N25: =IFERROR(AVERAGE(C25:L25),0) -> 2.1261209 | O25: =IFERROR(MEDIAN(D25:L25),0) -> 1.0794784
B27: Debtor Turnover Ratio | C27: =IFERROR(('Historical FS'!C6/'Historical FS'!C59),0) -> 20.119918 | D27: =IFERROR(('Historical FS'!D6/'Historical FS'!D59),0) -> 19.160353 | E27: =IFERROR(('Historical FS'!E6/'Historical FS'!E59),0) -> 14.655712 | F27: =IFERROR(('Historical FS'!F6/'Historical FS'!F59),0) -> 15.894699 | G27: =IFERROR(('Historical FS'!G6/'Historical FS'!G59),0) -> 23.366617 | H27: =IFERROR(('Historical FS'!H6/'Historical FS'!H59),0) -> 19.701331 | I27: =IFERROR(('Historical FS'!I6/'Historical FS'!I59),0) -> 22.379918 | J27: =IFERROR(('Historical FS'!J6/'Historical FS'!J59),0) -> 21.982948 | ... L27: =IFERROR(('Historical FS'!L6/'Historical FS'!L59),0) -> 33.189538 | N27: =IFERROR(AVERAGE(C27:L27),0) -> 21.605368 | O27: =IFERROR(MEDIAN(D27:L27),0) -> 21.982948
B28: Creditor Turnover Ratio | C28: =IFERROR('Historical FS'!C6/'Historical FS'!C50,0) -> 2.3769604 | D28: =IFERROR('Historical FS'!D6/'Historical FS'!D50,0) -> 1.9842808 | E28: =IFERROR('Historical FS'!E6/'Historical FS'!E50,0) -> 2.041478 | F28: =IFERROR('Historical FS'!F6/'Historical FS'!F50,0) -> 2.1667848 | G28: =IFERROR('Historical FS'!G6/'Historical FS'!G50,0) -> 1.9731057 | H28: =IFERROR('Historical FS'!H6/'Historical FS'!H50,0) -> 1.7323685 | I28: =IFERROR('Historical FS'!I6/'Historical FS'!I50,0) -> 2.0170312 | J28: =IFERROR('Historical FS'!J6/'Historical FS'!J50,0) -> 2.2286057 | ... L28: =IFERROR('Historical FS'!L6/'Historical FS'!L50,0) -> 2.3228767 | N28: =IFERROR(AVERAGE(C28:L28),0) -> 2.1290872 | O28: =IFERROR(MEDIAN(D28:L28),0) -> 2.041478
B29: Inventory Turnover Ratio | C29: =IFERROR('Historical FS'!C6/'Historical FS'!C60,0) -> 8.3613381 | D29: =IFERROR('Historical FS'!D6/'Historical FS'!D60,0) -> 7.6867643 | E29: =IFERROR('Historical FS'!E6/'Historical FS'!E60,0) -> 6.9190052 | F29: =IFERROR('Historical FS'!F6/'Historical FS'!F60,0) -> 7.7392856 | G29: =IFERROR('Historical FS'!G6/'Historical FS'!G60,0) -> 6.9698269 | H29: =IFERROR('Historical FS'!H6/'Historical FS'!H60,0) -> 6.9217099 | I29: =IFERROR('Historical FS'!I6/'Historical FS'!I60,0) -> 7.9015588 | J29: =IFERROR('Historical FS'!J6/'Historical FS'!J60,0) -> 8.4888642 | ... L29: =IFERROR('Historical FS'!L6/'Historical FS'!L60,0) -> 9.3019738 | N29: =IFERROR(AVERAGE(C29:L29),0) -> 7.937244 | O29: =IFERROR(MEDIAN(D29:L29),0) -> 7.7392856
B30: Fixed Assest Turnover Ratio | C30: =IFERROR('Historical FS'!C6/'Historical FS'!C53,0) -> 2.5463128 | D30: =IFERROR('Historical FS'!D6/'Historical FS'!D53,0) -> 2.8109343 | E30: =IFERROR('Historical FS'!E6/'Historical FS'!E53,0) -> 2.4012949 | F30: =IFERROR('Historical FS'!F6/'Historical FS'!F53,0) -> 2.714432 | G30: =IFERROR('Historical FS'!G6/'Historical FS'!G53,0) -> 2.0539206 | H30: =IFERROR('Historical FS'!H6/'Historical FS'!H53,0) -> 1.8008727 | I30: =IFERROR('Historical FS'!I6/'Historical FS'!I53,0) -> 2.0053489 | J30: =IFERROR('Historical FS'!J6/'Historical FS'!J53,0) -> 2.6193792 | ... L30: =IFERROR('Historical FS'!L6/'Historical FS'!L53,0) -> 3.800401 | N30: =IFERROR(AVERAGE(C30:L30),0) -> 2.6331377 | O30: =IFERROR(MEDIAN(D30:L30),0) -> 2.6193792
B31: Capital Turnover Ratio | C31: =IFERROR('Historical FS'!C6/SUM('Historical FS'!C47:C48),0) -> 3.4583567 | D31: =IFERROR('Historical FS'!D6/SUM('Historical FS'!D47:D48),0) -> 4.6449144 | E31: =IFERROR('Historical FS'!E6/SUM('Historical FS'!E47:E48),0) -> 3.0551909 | F31: =IFERROR('Historical FS'!F6/SUM('Historical FS'!F47:F48),0) -> 5.0172916 | G31: =IFERROR('Historical FS'!G6/SUM('Historical FS'!G47:G48),0) -> 4.138777 | H31: =IFERROR('Historical FS'!H6/SUM('Historical FS'!H47:H48),0) -> 4.5214404 | I31: =IFERROR('Historical FS'!I6/SUM('Historical FS'!I47:I48),0) -> 6.2487853 | J31: =IFERROR('Historical FS'!J6/SUM('Historical FS'!J47:J48),0) -> 7.6335681 | ... L31: =IFERROR('Historical FS'!L6/SUM('Historical FS'!L47:L48),0) -> 3.7857746 | N31: =IFERROR(AVERAGE(C31:L31),0) -> 4.76151 | O31: =IFERROR(MEDIAN(D31:L31),0) -> 4.6449144
B33: Debtor Days | C33: =IFERROR(365/C27,0) -> 18.141227 | D33: =IFERROR(365/D27,0) -> 19.049753 | E33: =IFERROR(365/E27,0) -> 24.904965 | F33: =IFERROR(365/F27,0) -> 22.963631 | G33: =IFERROR(365/G27,0) -> 15.620575 | H33: =IFERROR(365/H27,0) -> 18.526667 | I33: =IFERROR(365/I27,0) -> 16.309265 | J33: =IFERROR(365/J27,0) -> 16.603779 | ... L33: =IFERROR(365/L27,0) -> 10.997441 | N33: =IFERROR(AVERAGE(C33:L33),0) -> 17.737364 | O33: =IFERROR(MEDIAN(D33:L33),0) -> 16.603779
B34: Payable Days | C34: =IFERROR(365/C28,0) -> 153.55746 | D34: =IFERROR(365/D28,0) -> 183.94574 | E34: =IFERROR(365/E28,0) -> 178.79203 | F34: =IFERROR(365/F28,0) -> 168.45236 | G34: =IFERROR(365/G28,0) -> 184.98755 | H34: =IFERROR(365/H28,0) -> 210.69421 | I34: =IFERROR(365/I28,0) -> 180.95902 | J34: =IFERROR(365/J28,0) -> 163.77953 | ... L34: =IFERROR(365/L28,0) -> 157.13275 | N34: =IFERROR(AVERAGE(C34:L34),0) -> 173.14397 | O34: =IFERROR(MEDIAN(D34:L34),0) -> 178.79203
B35: Inventory Days | C35: =IFERROR(365/C29,0) -> 43.6533 | D35: =IFERROR(365/D29,0) -> 47.484219 | E35: =IFERROR(365/E29,0) -> 52.753249 | F35: =IFERROR(365/F29,0) -> 47.161976 | G35: =IFERROR(365/G29,0) -> 52.368589 | H35: =IFERROR(365/H29,0) -> 52.732635 | I35: =IFERROR(365/I29,0) -> 46.193417 | J35: =IFERROR(365/J29,0) -> 42.997507 | ... L35: =IFERROR(365/L29,0) -> 39.238984 | N35: =IFERROR(AVERAGE(C35:L35),0) -> 46.477276 | O35: =IFERROR(MEDIAN(D35:L35),0) -> 47.161976
B36: Cash Conversion Cycle (in days) | C36: =IFERROR(SUM(C33,C35)-C34,0) -> -91.762933 | D36: =IFERROR(SUM(D33,D35)-D34,0) -> -117.41177 | E36: =IFERROR(SUM(E33,E35)-E34,0) -> -101.13382 | F36: =IFERROR(SUM(F33,F35)-F34,0) -> -98.326751 | G36: =IFERROR(SUM(G33,G35)-G34,0) -> -116.99839 | H36: =IFERROR(SUM(H33,H35)-H34,0) -> -139.4349 | I36: =IFERROR(SUM(I33,I35)-I34,0) -> -118.45634 | J36: =IFERROR(SUM(J33,J35)-J34,0) -> -104.17824 | ... L36: =IFERROR(SUM(L33,L35)-L34,0) -> -106.89633 | N36: =IFERROR(AVERAGE(C36:L36),0) -> -108.92933 | O36: =IFERROR(MEDIAN(D36:L36),0) -> -106.89633
B38: CFO/Sales | C38: =IFERROR('Historical FS'!C78/'Historical FS'!C6,0) -> 0.14360971 | D38: =IFERROR('Historical FS'!D78/'Historical FS'!D6,0) -> 0.12404497 | E38: =IFERROR('Historical FS'!E78/'Historical FS'!E6,0) -> 0.059759806 | F38: =IFERROR('Historical FS'!F78/'Historical FS'!F6,0) -> 0.03865358 | G38: =IFERROR('Historical FS'!G78/'Historical FS'!G6,0) -> 0.12141666 | H38: =IFERROR('Historical FS'!H78/'Historical FS'!H6,0) -> 0.11572301 | I38: =IFERROR('Historical FS'!I78/'Historical FS'!I6,0) -> 0.012684339 | J38: =IFERROR('Historical FS'!J78/'Historical FS'!J6,0) -> 0.093248786 | ... L38: =IFERROR('Historical FS'!L78/'Historical FS'!L6,0) -> 0.16206234 | N38: =IFERROR(AVERAGE(C38:L38),0) -> 0.10445609 | O38: =IFERROR(MEDIAN(D38:L38),0) -> 0.11572301
B39: CFO/Total Assets | C39: =IFERROR('Historical FS'!C78/'Historical FS'!C64,0) -> 0.14899075 | D39: =IFERROR('Historical FS'!D78/'Historical FS'!D64,0) -> 0.12273078 | E39: =IFERROR('Historical FS'!E78/'Historical FS'!E64,0) -> 0.05325011 | F39: =IFERROR('Historical FS'!F78/'Historical FS'!F64,0) -> 0.038177516 | G39: =IFERROR('Historical FS'!G78/'Historical FS'!G64,0) -> 0.099000751 | H39: =IFERROR('Historical FS'!H78/'Historical FS'!H64,0) -> 0.08462982 | I39: =IFERROR('Historical FS'!I78/'Historical FS'!I64,0) -> 0.010733556 | J39: =IFERROR('Historical FS'!J78/'Historical FS'!J64,0) -> 0.096395174 | ... L39: =IFERROR('Historical FS'!L78/'Historical FS'!L64,0) -> 0.1890268 | N39: =IFERROR(AVERAGE(C39:L39),0) -> 0.10465502 | O39: =IFERROR(MEDIAN(D39:L39),0) -> 0.096395174
B40: CFO/Total Debt | C40: =IFERROR('Historical FS'!C78/'Historical FS'!C49,0) -> 0.56534058 | D40: =IFERROR('Historical FS'!D78/'Historical FS'!D49,0) -> 0.42560186 | E40: =IFERROR('Historical FS'!E78/'Historical FS'!E49,0) -> 0.19587305 | F40: =IFERROR('Historical FS'!F78/'Historical FS'!F49,0) -> 0.10992195 | G40: =IFERROR('Historical FS'!G78/'Historical FS'!G49,0) -> 0.25401554 | H40: =IFERROR('Historical FS'!H78/'Historical FS'!H49,0) -> 0.20338341 | I40: =IFERROR('Historical FS'!I78/'Historical FS'!I49,0) -> 0.024117606 | J40: =IFERROR('Historical FS'!J78/'Historical FS'!J49,0) -> 0.24055009 | ... L40: =IFERROR('Historical FS'!L78/'Historical FS'!L49,0) -> 0.99605815 | N40: =IFERROR(AVERAGE(C40:L40),0) -> 0.37163091 | O40: =IFERROR(MEDIAN(D40:L40),0) -> 0.24055009

Sheet Forecasting
B2: ='Data Sheet'!B1&" - "&'Data Sheet'!A17 -> TATA MOTORS PASSENGER VEHICLES LTD - Sales | G2: ='Data Sheet'!B1&" - "&'Historical FS'!B18 -> TATA MOTORS PASSENGER VEHICLES LTD - EBITDA | L2: ='Data Sheet'!B1&" - "&'Historical FS'!B38 -> TATA MOTORS PASSENGER VEHICLES LTD - Earning Per Share EPS
B3: Year Weight | C3: Year | D3: Sales | E3: Sales Growth | G3: Year Weight | H3: Year | I3: EBITDA | J3: EBITDA Growth | L3: Year Weight | M3: Year | N3: Earnings per Share | O3: EPS Growth
B4: 1 | C4: 2016 | D4: {=TRANSPOSE('Data Sheet'!B17:K17)} -> 273045.6 | G4: 1 | H4: =C4 -> 2016 | I4: {=TRANSPOSE('Historical FS'!C18:L18)} -> 38395.25 | L4: 1 | M4: 2016 | N4: {=TRANSPOSE('Historical FS'!C38:L38)} -> 47.694444
B5: =B4+1 -> 2 | C5: =C4+1 -> 2017 | D5: 269692.51 | E5: =IFERROR(D5/D4-1,0) -> -0.01228033 | G5: =G4+1 -> 2 | H5: =H4+1 -> 2017 | I5: 29588.69 | J5: =IFERROR(I5/I4-1,0) -> -0.22936587 | L5: =L4+1 -> 2 | M5: =M4+1 -> 2017 | N5: 14.527275 | O5: =IFERROR(N5/N4-1,0) -> -0.6954095
B6: =B5+1 -> 3 | C6: =C5+1 -> 2018 | D6: 291550.48 | E6: =IFERROR(D6/D5-1,0) -> 0.081047746 | G6: =G5+1 -> 3 | H6: =H5+1 -> 2018 | I6: 31457.68 | J6: =IFERROR(I6/I5-1,0) -> 0.063165689 | L6: =L5+1 -> 3 | M6: =M5+1 -> 2018 | N6: 3.0491116 | O6: =IFERROR(N6/N5-1,0) -> -0.79011124
B7: =B6+1 -> 4 | C7: =C6+1 -> 2019 | D7: 301938.4 | E7: =IFERROR(D7/D6-1,0) -> 0.035629919 | G7: =G6+1 -> 4 | H7: =H6+1 -> 2019 | I7: 24664.33 | J7: =IFERROR(I7/I6-1,0) -> -0.21595203 | L7: =L6+1 -> 4 | M7: =M6+1 -> 2019 | N7: -7.7839158 | O7: =IFERROR(N7/N6-1,0) -> -3.5528471
B8: =B7+1 -> 5 | C8: =C7+1 -> 2020 | D8: 261067.97 | E8: =IFERROR(D8/D7-1,0) -> -0.13536016 | G8: =G7+1 -> 5 | H8: =H7+1 -> 2020 | I8: 17987.07 | J8: =IFERROR(I8/I7-1,0) -> -0.27072538 | L8: =L7+1 -> 5 | M8: =M7+1 -> 2020 | N8: -35.859307 | O8: =IFERROR(N8/N7-1,0) -> 3.6068468
B9: =B8+1 -> 6 | C9: =C8+1 -> 2021 | D9: 249794.75 | E9: =IFERROR(D9/D8-1,0) -> -0.043181168 | G9: =G8+1 -> 6 | H9: =H8+1 -> 2021 | I9: 32287.43 | J9: =IFERROR(I9/I8-1,0) -> 0.79503554 | L9: =L8+1 -> 6 | M9: =M8+1 -> 2021 | N9: -5.7172846 | O9: =IFERROR(N9/N8-1,0) -> -0.84056344
B10: =B9+1 -> 7 | C10: =C9+1 -> 2022 | D10: 278453.62 | E10: =IFERROR(D10/D9-1,0) -> 0.11472967 | G10: =G9+1 -> 7 | H10: =H9+1 -> 2022 | I10: 24720.09 | J10: =IFERROR(I10/I9-1,0) -> -0.23437418 | L10: =L9+1 -> 7 | M10: =M9+1 -> 2022 | N10: -41.132141 | O10: =IFERROR(N10/N9-1,0) -> 6.194349
B11: =B10+1 -> 8 | C11: =C10+1 -> 2023 | D11: 345966.97 | E11: =IFERROR(D11/D10-1,0) -> 0.24245815 | G11: =G10+1 -> 8 | H11: =H10+1 -> 2023 | I11: 31815.8 | J11: =IFERROR(I11/I10-1,0) -> 0.28704224 | L11: =L10+1 -> 8 | M11: =M10+1 -> 2023 | N11: -11.965495 | O11: =IFERROR(N11/N10-1,0) -> -0.70909622
B12: =B11+1 -> 9 | C12: =C11+1 -> 2024 | D12: 434016 | E12: =IFERROR(D12/D11-1,0) -> 0.25450126 | G12: =G11+1 -> 9 | H12: =H11+1 -> 2024 | I12: 57809 | J12: =IFERROR(I12/I11-1,0) -> 0.8169903 | L12: =L11+1 -> 9 | M12: =M11+1 -> 2024 | N12: 81.234768 | O12: =IFERROR(N12/N11-1,0) -> -7.7890852
B13: =B12+1 -> 10 | C13: =C12+1 -> 2025 | D13: 439695 | E13: =IFERROR(D13/D12-1,0) -> 0.013084771 | G13: =G12+1 -> 10 | H13: =H12+1 -> 2025 | I13: 56138 | J13: =IFERROR(I13/I12-1,0) -> -0.028905534 | L13: =L12+1 -> 10 | M13: =M12+1 -> 2025 | N13: 46.986119 | O13: =IFERROR(N13/N12-1,0) -> -0.42160087
B14: =B13+1 -> 11 | C14: =C13+1 -> 2026 | D14: =IFERROR(FORECAST(B14,$D$4:$D$13,$B$4:$B$13),0) -> 409204.26 | E14: =IFERROR(D14/D13-1,0) -> -0.069345204 | G14: =G13+1 -> 11 | H14: =H13+1 -> 2026 | I14: =IFERROR(FORECAST(G14,$I$4:$I$13,$G$4:$G$13),0) -> 46935.839 | J14: =IFERROR(I14/I13-1,0) -> -0.16392035 | L14: =L13+1 -> 11 | M14: =M13+1 -> 2026 | N14: =IFERROR(FORECAST(G14,$N$4:$N$13,$L$4:$L$13),0) -> 19.623419 | O14: =IFERROR(N14/N13-1,0) -> -0.5823571
B15: =B14+1 -> 12 | C15: =C14+1 -> 2027 | D15: =IFERROR(FORECAST(B15,$D$4:$D$13,$B$4:$B$13),0) -> 426419.19 | E15: =IFERROR(D15/D14-1,0) -> 0.04206929 | G15: =G14+1 -> 12 | H15: =H14+1 -> 2027 | I15: =IFERROR(FORECAST(G15,$I$4:$I$13,$G$4:$G$13),0) -> 49199.386 | J15: =IFERROR(I15/I14-1,0) -> 0.048226397 | L15: =L14+1 -> 12 | M15: =M14+1 -> 2027 | N15: =IFERROR(FORECAST(G15,$N$4:$N$13,$L$4:$L$13),0) -> 21.536157 | O15: =IFERROR(N15/N14-1,0) -> 0.097472232
B16: =B15+1 -> 13 | C16: =C15+1 -> 2028 | D16: =IFERROR(FORECAST(B16,$D$4:$D$13,$B$4:$B$13),0) -> 443634.13 | E16: =IFERROR(D16/D15-1,0) -> 0.040370915 | G16: =G15+1 -> 13 | H16: =H15+1 -> 2028 | I16: =IFERROR(FORECAST(G16,$I$4:$I$13,$G$4:$G$13),0) -> 51462.932 | J16: =IFERROR(I16/I15-1,0) -> 0.046007616 | L16: =L15+1 -> 13 | M16: =M15+1 -> 2028 | N16: =IFERROR(FORECAST(G16,$N$4:$N$13,$L$4:$L$13),0) -> 23.448896 | O16: =IFERROR(N16/N15-1,0) -> 0.088815215
B17: =B16+1 -> 14 | C17: =C16+1 -> 2029 | D17: =IFERROR(FORECAST(B17,$D$4:$D$13,$B$4:$B$13),0) -> 460849.06 | E17: =IFERROR(D17/D16-1,0) -> 0.038804348 | G17: =G16+1 -> 14 | H17: =H16+1 -> 2029 | I17: =IFERROR(FORECAST(G17,$I$4:$I$13,$G$4:$G$13),0) -> 53726.479 | J17: =IFERROR(I17/I16-1,0) -> 0.043984016 | L17: =L16+1 -> 14 | M17: =M16+1 -> 2029 | N17: =IFERROR(FORECAST(G17,$N$4:$N$13,$L$4:$L$13),0) -> 25.361634 | O17: =IFERROR(N17/N16-1,0) -> 0.081570512
B18: =B17+1 -> 15 | C18: =C17+1 -> 2030 | D18: =IFERROR(FORECAST(B18,$D$4:$D$13,$B$4:$B$13),0) -> 478063.99 | E18: =IFERROR(D18/D17-1,0) -> 0.037354818 | G18: =G17+1 -> 15 | H18: =H17+1 -> 2030 | I18: =IFERROR(FORECAST(G18,$I$4:$I$13,$G$4:$G$13),0) -> 55990.025 | J18: =IFERROR(I18/I17-1,0) -> 0.042130928 | L18: =L17+1 -> 15 | M18: =M17+1 -> 2030 | N18: =IFERROR(FORECAST(G18,$N$4:$N$13,$L$4:$L$13),0) -> 27.274372 | O18: =IFERROR(N18/N17-1,0) -> 0.07541858

Sheet Data>

Sheet Data Sheet
A1: COMPANY NAME | B1: TATA MOTORS PASSENGER VEHICLES LTD | E1: =IF(B2<>B3, "A NEW VERSION OF THE WORKSHEET IS AVAILABLE", "")
A2: LATEST VERSION | B2: 2.1 | E2: PLEASE DO NOT MAKE ANY CHANGES TO THIS SHEET
A3: CURRENT VERSION | B3: 2.1
A5: META
A6: Number of shares | B6: =IF(B9>0, B9/B8, 0) -> 368.23789
A7: Face Value | B7: 2
A8: Current Price | B8: 301.9
A9: Market Capitalization | B9: 111171.02
A15: PROFIT & LOSS
A16: Report Date | B16: 42460 | C16: 42825 | D16: 43190 | E16: 43555 | F16: 43921 | G16: 44286 | H16: 44651 | I16: 45016 | J16: 45382 | K16: 45747
A17: Sales | B17: 273045.6 | C17: 269692.51 | D17: 291550.48 | E17: 301938.4 | F17: 261067.97 | G17: 249794.75 | H17: 278453.62 | I17: 345966.97 | J17: 434016 | K17: 439695
A18: Raw Material Cost | B18: 166134.01 | C18: 173294.08 | D18: 187896.58 | E18: 194267.91 | F18: 164899.82 | G18: 153607.36 | H18: 179295.33 | I18: 231251.26 | J18: 274321 | K18: 268950
A19: Change in Inventory | B19: 2750.99 | C19: 7399.92 | D19: 2046.58 | E19: -2053.28 | F19: -2231.19 | G19: -4684.16 | H19: -1590.49 | I19: 4781.62 | J19: 1566 | K19: -2836
A20: Power and Fuel | B20: 1143.63 | C20: 1159.82 | D20: 1308.08 | E20: 1585.93 | F20: 1264.95 | G20: 1112.87 | H20: 2178.29 | I20: 2513.33 | J20: 2189 | K20: 2443
A21: Other Mfr. Exp | B21: 12101.53 | C21: 10067.37 | D21: 10971.66 | E21: 11694.54 | F21: 11541.51 | G21: 8273.17 | H21: 9427.38 | I21: 11765.97 | J21: 17446 | K21: 18813
A22: Employee Cost | B22: 28880.89 | C22: 28332.89 | D22: 30300.09 | E22: 33243.87 | F22: 30438.6 | G22: 27648.48 | H22: 30808.52 | I22: 33654.7 | J22: 41990 | K22: 47767
A23: Selling and admin | B23: 21991.9 | C23: 30039.38 | D23: 31004.58 | E23: 32719.8 | F23: 29248.32 | G23: 23015.79 | H23: 29205.4 | I23: 34839.19 | J23: 42765 | K23: 47099
A24: Other Expenses | B24: 7149.38 | C24: 4610.2 | D24: 658.39 | E24: 1708.74 | F24: 3456.51 | G24: -834.51 | H24: 1228.12 | I24: 4908.34 | J24: -938 | K24: -4351
A25: Other Income | B25: -2669.62 | C25: 1869.1 | D25: 5932.73 | E25: -26686.25 | F25: 101.71 | G25: -11117.83 | H25: 2424.05 | I25: 6663.97 | J25: 4807 | K25: 10852
A26: Depreciation | B26: 16710.78 | C26: 17904.99 | D26: 21553.59 | E26: 23590.63 | F26: 21425.43 | G26: 23546.71 | H26: 24835.69 | I26: 24860.36 | J26: 27239 | K26: 23256
A27: Interest | B27: 4889.08 | C27: 4238.01 | D27: 4681.79 | E27: 5758.6 | F27: 7243.33 | G27: 8097.17 | H27: 9311.86 | I27: 10225.48 | J27: 7594 | K27: 5083
... A30: Net profit | B30: 11579.31 | C30: 7454.36 | D30: 8988.91 | E30: -28826.23 | F30: -12070.85 | G30: -13451.39 | H30: -11441.47 | I30: 2414.29 | J30: 31399 | K30: 27830
A31: Dividend Amount | B31: 67.92 | I31: 766.02 | J31: 2301 | K31: 2208
A40: Quarters
A41: Report Date | B41: 45199 | C41: 45291 | D41: 45382 | E41: 45473 | F41: 45565 | G41: 45657 | H41: 45747 | I41: 45838 | J41: 45930 | K41: 46022
A42: Sales | B42: 105129 | C42: 110577 | D42: 119033 | E42: 107102 | F42: 83656 | G42: 94472 | H42: 119503 | I42: 87677 | J42: 72349 | K42: 70108
A43: Expenses | B43: 91362 | C43: 95159 | D43: 102348 | E43: 91854 | F43: 73742 | G43: 84070 | H43: 102685 | I43: 79515 | J43: 73753 | K43: 69229
A44: Other Income | B44: 1557 | C44: 1604 | D44: 1412 | E44: 6553 | F44: 1920 | G44: 2730 | H44: 1057 | I44: 2690 | J44: 81507 | K44: 39
A45: Depreciation | B45: 6637 | C45: 6850 | D45: 7143 | E45: 6565 | F45: 5467 | G45: 4863 | H45: 5295 | I45: 4851 | J45: 4871 | K45: 4969
A46: Interest | B46: 2652 | C46: 2485 | D46: 1645 | E46: 1471 | F46: 1094 | G46: 843 | H46: 1076 | I46: 692 | J46: 686 | K46: 682
A47: Profit before tax | B47: 6035 | C47: 7687 | D47: 9309 | E47: 13765 | F47: 5273 | G47: 7426 | H47: 11504 | I47: 5309 | J47: 74546 | K47: -4733
A48: Tax | B48: 2203 | C48: 542 | D48: -8219 | E48: 3178 | F48: 1752 | G48: 1942 | H48: 2948 | I48: 1306 | J48: -1702 | K48: -1250
A49: Net profit | B49: 3764 | C49: 7025 | D49: 17407 | E49: 10514 | F49: 3446 | G49: 5406 | H49: 8470 | I49: 3924 | J49: 76170 | K49: -3486
A50: Operating Profit | B50: 13767 | C50: 15418 | D50: 16685 | E50: 15248 | F50: 9914 | G50: 10402 | H50: 16818 | I50: 8162 | J50: -1404 | K50: 879
A55: BALANCE SHEET
A56: Report Date | B56: 42460 | C56: 42825 | D56: 43190 | E56: 43555 | F56: 43921 | G56: 44286 | H56: 44651 | I56: 45016 | J56: 45382 | K56: 45747
A57: Equity Share Capital | B57: 679.18 | C57: 679.22 | D57: 679.22 | E57: 679.22 | F57: 719.54 | G57: 765.81 | H57: 765.88 | I57: 766.02 | J57: 767 | K57: 736
A58: Reserves | B58: 78273.23 | C58: 57382.67 | D58: 94748.69 | E58: 59500.34 | F58: 62358.99 | G58: 54480.91 | H58: 43795.36 | I58: 44555.77 | J58: 84151 | K58: 115408
A59: Borrowings | B59: 69359.96 | C59: 78603.98 | D59: 88950.47 | E59: 106175.34 | F59: 124787.64 | G59: 142130.57 | H59: 146449.03 | I59: 134113.44 | J59: 107264 | K59: 71540
A60: Other Liabilities | B60: 114871.75 | C60: 135914.49 | D60: 142813.43 | E60: 139348.59 | F60: 132313.22 | G60: 144192.62 | H60: 138051.22 | I60: 155239.2 | J60: 177339 | K60: 189289
A61: Total | B61: 263184.12 | C61: 272580.36 | D61: 327191.81 | E61: 305703.49 | F61: 320179.39 | G61: 341569.91 | H61: 329061.49 | I61: 334674.43 | J61: 369521 | K61: 376973
A62: Net Block | B62: 107231.76 | C62: 95944.08 | D62: 121413.86 | E62: 111234.47 | F62: 127107.14 | G62: 138707.61 | H62: 138855.45 | I62: 132079.76 | J62: 121285 | K62: 115697
A63: Capital Work in Progress | B63: 25918.94 | C63: 33698.84 | D63: 40033.5 | E63: 31883.84 | F63: 35622.29 | G63: 20963.93 | H63: 10251.09 | I63: 14274.5 | J63: 35698 | K63: 65806
A64: Investments | B64: 23767.02 | C64: 20337.92 | D64: 20812.75 | E64: 15770.72 | F64: 16308.48 | G64: 24620.28 | H64: 29379.53 | I64: 26379.16 | J64: 22971 | K64: 35656
A65: Other Assets | B65: 106266.4 | C65: 122599.52 | D65: 144931.7 | E65: 146814.46 | F65: 141141.48 | G65: 157278.09 | H65: 150575.42 | I65: 161941.01 | J65: 189567 | K65: 159814
A66: Total | B66: 263184.12 | C66: 272580.36 | D66: 327191.81 | E66: 305703.49 | F66: 320179.39 | G66: 341569.91 | H66: 329061.49 | I66: 334674.43 | J66: 369521 | K66: 376973
A67: Receivables | B67: 13570.91 | C67: 14075.55 | D67: 19893.3 | E67: 18996.17 | F67: 11172.69 | G67: 12679.08 | H67: 12442.12 | I67: 15737.97 | J67: 16952 | K67: 13248
... A70: No. of Equity Shares | B70: 3395930306 | C70: 3396100719 | D70: 3396100719 | E70: 3396100719 | F70: 3597726185 | G70: 3829060661 | H70: 3829414903 | I70: 3830097221 | J70: 3832491897 | K70: 3681348742
A71: New Bonus Shares
A72: Face value | B72: 2 | C72: 2 | D72: 2 | E72: 2 | F72: 2 | G72: 2 | H72: 2 | I72: 2 | J72: 2 | K72: 2
A80: CASH FLOW:
A81: Report Date | B81: 42460 | C81: 42825 | D81: 43190 | E81: 43555 | F81: 43921 | G81: 44286 | H81: 44651 | I81: 45016 | J81: 45382 | K81: 45747
A82: Cash from Operating Activity | B82: 37899.54 | C82: 30199.25 | D82: 23857.42 | E82: 18890.75 | F82: 26632.94 | G82: 29000.51 | H82: 14282.83 | I82: 35388.01 | J82: 67915 | K82: 63102
A83: Cash from Investing Activity | B83: -36693.9 | C83: -39571.4 | D83: -25139.14 | E83: -20878.07 | F83: -33114.55 | G83: -25672.5 | H83: -4443.66 | I83: -15417.17 | J83: -22781 | K83: -49982
A84: Cash from Financing Activity | B84: -3795.12 | C84: 6205.3 | D84: 2011.71 | E84: 8830.37 | F84: 3389.61 | G84: 9904.2 | H84: -3380.17 | I84: -26242.9 | J84: -37006 | K84: -18786
A85: Net Cash Flow | B85: -2589.48 | C85: -3166.85 | D85: 729.99 | E85: 6843.05 | F85: -3092 | G85: 13232.21 | H85: 6459 | I85: -6272.06 | J85: 8128 | K85: -5666
A90: PRICE: | B90: 233.55 | C90: 281.43 | D90: 197.46 | E90: 105.27 | F90: 42.92 | G90: 182.32 | H90: 262.04 | I90: 254.22 | J90: 599.77 | K90: 407.45
A92: DERIVED:
A93: Adjusted Equity Shares in Cr | B93: 288.72 | C93: 288.73 | D93: 288.73 | E93: 288.73 | F93: 308.9 | G93: 332.03 | H93: 332.07 | I93: 332.13 | J93: 332.37 | K93: 368.13

Sheet Cash Flow Data
C2: 41699 | D2: 42064 | E2: 42430 | F2: 42795 | G2: 43160 | H2: 43525 | I2: 43891 | J2: 44256 | K2: 44621 | L2: 44986 | M2: 45352 | N2: 45717
B3: Cash from Operating Activities | C3: 36151 | D3: 35531 | E3: 37900 | F3: 30199 | G3: 23857 | H3: 18891 | I3: 26633 | J3: 29001 | K3: 14283 | L3: 35388 | M3: 67915 | N3: 63102
B4: Profit from operations | C4: 36303 | D4: 43397 | E4: 38626 | F4: 28840 | G4: 33312 | H4: 28771 | I4: 23352 | J4: 31198 | K4: 26943 | L4: 41694 | M4: 65106 | N4: 58937
B5: Receivables | C5: 445 | D5: -3179 | E5: -2223 | F5: -4152 | G5: -10688 | H5: -9109 | I5: 9950 | J5: -5505 | K5: 185 | L5: -2213 | M5: -1876 | N5: 3573
B6: Inventory | C6: -2853 | D6: -3692 | E6: -5743 | F6: -6621 | G6: -3560 | H6: 2069 | I6: 2326 | J6: 3814 | K6: 472 | L6: -5665 | M6: -7265 | N6: 2127
B7: Payables | C7: 4694 | D7: 3598 | E7: 3947 | F7: 9301 | G7: 7320 | H7: -4692 | I7: -8085 | J7: 5748 | K7: -7012 | L7: 6945 | M7: 13706 | N7: 1303
B8: Loans Advances | C8: 0 | D8: 0 | E8: -520 | F8: 0 | G8: 0 | H8: 0 | I8: 0 | J8: 0 | K8: 0 | L8: 0 | M8: 0 | N8: 0
B9: Other WC items | C9: 1870 | D9: -398 | E9: 5852 | F9: 4727 | G9: 494 | H9: 4512 | I9: 875 | J9: -4150 | K9: -4396 | L9: -2194 | M9: 2760 | N9: 1153
B10: Working capital changes | C10: 4157 | D10: -3672 | E10: 1313 | F10: 3254 | G10: -6434 | H10: -7221 | I10: 5065 | J10: -93 | K10: -10750 | L10: -3127 | M10: 7325 | N10: 8156
B11: Direct taxes | C11: -4308 | D11: -4194 | E11: -2040 | F11: -1895 | G11: -3021 | H11: -2659 | I11: -1785 | J11: -2105 | K11: -1910 | L11: -3179 | M11: -4516 | N11: -3991
B12: Cash from Investing Activities | C12: -27991 | D12: -36232 | E12: -36694 | F12: -39571 | G12: -25139 | H12: -20878 | I12: -33115 | J12: -25672 | K12: -4444 | L12: -15417 | M12: -22781 | N12: -49982
B13: Fixed assets purchased | C13: -26975 | D13: -31962 | E13: -31503 | F13: -16072 | G13: -35079 | H13: -35304 | I13: -29702 | J13: -20205 | K13: -15168 | L13: -19230 | M13: -31414 | N13: -38042
B14: Fixed assets sold | C14: 50 | D14: 74 | E14: 59 | F14: 53 | G14: 30 | H14: 67 | I14: 171 | J14: 351 | K14: 230 | L14: 285 | M14: 231 | N14: 974
... B35: CFO/OP | C35: 1.16 | D35: 1.01 | E35: 1.04 | F35: 1.08 | G35: 0.85 | H35: 0.87 | I35: 1.58 | J35: 0.96 | K35: 0.66 | L35: 1.21 | M35: 1.25 | N35: 1.2
